[
  {
    "SERIES": "SE_ADT_NMRCY",
    "FREQ": "A",
    "REFAREA": "AUT",
    "LOCATION": "T",
    "AGEGROUP": "016_050_Y",
    "SEX": "F",
    "TIMEPERIOD": "2012",
    "UNIT": "PERCENT",
    "UNITMULT": "0",
    "OBSVALUE": "96.331589989",
    "NATURE": "C",
    "SOURCETYPE": "NA",
    "SOURCEDETAIL": "PIAAC (Programme for the International Assessment of Adult Competencies)",
    "TIMEDETAIL": "2012",
    "FOOTNOTES": "Level of Assessment Reflecting Minimum Achievement equals 1"
  },
  {
    "SERIES": "SE_ADT_NMRCY",
    "FREQ": "A",
    "REFAREA": "BEL",
    "LOCATION": "T",
    "AGEGROUP": "016_050_Y",
    "SEX": "F",
    "TIMEPERIOD": "2012",
    "UNIT": "PERCENT",
    "UNITMULT": "0",
    "OBSVALUE": "96.5868386466",
    "NATURE": "C",
    "SOURCETYPE": "NA",
    "SOURCEDETAIL": "PIAAC (Programme for the International Assessment of Adult Competencies)",
    "TIMEDETAIL": "2012",
    "FOOTNOTES": "Level of Assessment Reflecting Minimum Achievement equals 1, Belgium (Flemish)"
  },
  {
    "SERIES": "SE_ADT_NMRCY",
    "FREQ": "A",
    "REFAREA": "CAN",
    "LOCATION": "T",
    "AGEGROUP": "016_050_Y",
    "SEX": "F",
    "TIMEPERIOD": "2012",
    "UNIT": "PERCENT",
    "UNITMULT": "0",
    "OBSVALUE": "93.0232926559",
    "NATURE": "C",
    "SOURCETYPE": "NA",
    "SOURCEDETAIL": "PIAAC (Programme for the International Assessment of Adult Competencies)",
    "TIMEDETAIL": "2012",
    "FOOTNOTES": "Level of Assessment Reflecting Minimum Achievement equals 1"
  },
  {
    "SERIES": "SE_ADT_NMRCY",
    "FREQ": "A",
    "REFAREA": "CZE",
    "LOCATION": "T",
    "AGEGROUP": "016_050_Y",
    "SEX": "F",
    "TIMEPERIOD": "2012",
    "UNIT": "PERCENT",
    "UNITMULT": "0",
    "OBSVALUE": "97.8922331663",
    "NATURE": "C",
    "SOURCETYPE": "NA",
    "SOURCEDETAIL": "PIAAC (Programme for the International Assessment of Adult Competencies)",
    "TIMEDETAIL": "2012",
    "FOOTNOTES": "Level of Assessment Reflecting Minimum Achievement equals 1"
  },
  {
    "SERIES": "SE_ADT_NMRCY",
    "FREQ": "A",
    "REFAREA": "DEU",
    "LOCATION": "T",
    "AGEGROUP": "016_050_Y",
    "SEX": "F",
    "TIMEPERIOD": "2012",
    "UNIT": "PERCENT",
    "UNITMULT": "0",
    "OBSVALUE": "94.2019621128",
    "NATURE": "C",
    "SOURCETYPE": "NA",
    "SOURCEDETAIL": "PIAAC (Programme for the International Assessment of Adult Competencies)",
    "TIMEDETAIL": "2012",
    "FOOTNOTES": "Level of Assessment Reflecting Minimum Achievement equals 1"
  },
  {
    "SERIES": "SE_ADT_NMRCY",
    "FREQ": "A",
    "REFAREA": "DNK",
    "LOCATION": "T",
    "AGEGROUP": "016_050_Y",
    "SEX": "F",
    "TIMEPERIOD": "2012",
    "UNIT": "PERCENT",
    "UNITMULT": "0",
    "OBSVALUE": "96.5410767282",
    "NATURE": "C",
    "SOURCETYPE": "NA",
    "SOURCEDETAIL": "PIAAC (Programme for the International Assessment of Adult Competencies)",
    "TIMEDETAIL": "2012",
    "FOOTNOTES": "Level of Assessment Reflecting Minimum Achievement equals 1"
  },
  {
    "SERIES": "SE_ADT_NMRCY",
    "FREQ": "A",
    "REFAREA": "ESP",
    "LOCATION": "T",
    "AGEGROUP": "016_050_Y",
    "SEX": "F",
    "TIMEPERIOD": "2012",
    "UNIT": "PERCENT",
    "UNITMULT": "0",
    "OBSVALUE": "89.0662023014",
    "NATURE": "C",
    "SOURCETYPE": "NA",
    "SOURCEDETAIL": "PIAAC (Programme for the International Assessment of Adult Competencies)",
    "TIMEDETAIL": "2012",
    "FOOTNOTES": "Level of Assessment Reflecting Minimum Achievement equals 1"
  },
  {
    "SERIES": "SE_ADT_NMRCY",
    "FREQ": "A",
    "REFAREA": "EST",
    "LOCATION": "T",
    "AGEGROUP": "016_050_Y",
    "SEX": "F",
    "TIMEPERIOD": "2012",
    "UNIT": "PERCENT",
    "UNITMULT": "0",
    "OBSVALUE": "97.8541509313",
    "NATURE": "C",
    "SOURCETYPE": "NA",
    "SOURCEDETAIL": "PIAAC (Programme for the International Assessment of Adult Competencies)",
    "TIMEDETAIL": "2012",
    "FOOTNOTES": "Level of Assessment Reflecting Minimum Achievement equals 1"
  },
  {
    "SERIES": "SE_ADT_NMRCY",
    "FREQ": "A",
    "REFAREA": "FIN",
    "LOCATION": "T",
    "AGEGROUP": "016_050_Y",
    "SEX": "F",
    "TIMEPERIOD": "2012",
    "UNIT": "PERCENT",
    "UNITMULT": "0",
    "OBSVALUE": "96.8155832192",
    "NATURE": "C",
    "SOURCETYPE": "NA",
    "SOURCEDETAIL": "PIAAC (Programme for the International Assessment of Adult Competencies)",
    "TIMEDETAIL": "2012",
    "FOOTNOTES": "Level of Assessment Reflecting Minimum Achievement equals 1"
  },
  {
    "SERIES": "SE_ADT_NMRCY",
    "FREQ": "A",
    "REFAREA": "FRA",
    "LOCATION": "T",
    "AGEGROUP": "016_050_Y",
    "SEX": "F",
    "TIMEPERIOD": "2012",
    "UNIT": "PERCENT",
    "UNITMULT": "0",
    "OBSVALUE": "89.7753447773",
    "NATURE": "C",
    "SOURCETYPE": "NA",
    "SOURCEDETAIL": "PIAAC (Programme for the International Assessment of Adult Competencies)",
    "TIMEDETAIL": "2012",
    "FOOTNOTES": "Level of Assessment Reflecting Minimum Achievement equals 1"
  },
  {
    "SERIES": "SE_ADT_NMRCY",
    "FREQ": "A",
    "REFAREA": "GBR",
    "LOCATION": "T",
    "AGEGROUP": "016_050_Y",
    "SEX": "F",
    "TIMEPERIOD": "2012",
    "UNIT": "PERCENT",
    "UNITMULT": "0",
    "OBSVALUE": "92.7146040996",
    "NATURE": "C",
    "SOURCETYPE": "NA",
    "SOURCEDETAIL": "PIAAC (Programme for the International Assessment of Adult Competencies)",
    "TIMEDETAIL": "2012",
    "FOOTNOTES": "Level of Assessment Reflecting Minimum Achievement equals 1, UK comprises England and North Irland"
  },
  {
    "SERIES": "SE_ADT_NMRCY",
    "FREQ": "A",
    "REFAREA": "IRL",
    "LOCATION": "T",
    "AGEGROUP": "016_050_Y",
    "SEX": "F",
    "TIMEPERIOD": "2012",
    "UNIT": "PERCENT",
    "UNITMULT": "0",
    "OBSVALUE": "92.4155666386",
    "NATURE": "C",
    "SOURCETYPE": "NA",
    "SOURCEDETAIL": "PIAAC (Programme for the International Assessment of Adult Competencies)",
    "TIMEDETAIL": "2012",
    "FOOTNOTES": "Level of Assessment Reflecting Minimum Achievement equals 1"
  },
  {
    "SERIES": "SE_ADT_NMRCY",
    "FREQ": "A",
    "REFAREA": "ITA",
    "LOCATION": "T",
    "AGEGROUP": "016_050_Y",
    "SEX": "F",
    "TIMEPERIOD": "2012",
    "UNIT": "PERCENT",
    "UNITMULT": "0",
    "OBSVALUE": "90.9329411491",
    "NATURE": "C",
    "SOURCETYPE": "NA",
    "SOURCEDETAIL": "PIAAC (Programme for the International Assessment of Adult Competencies)",
    "TIMEDETAIL": "2012",
    "FOOTNOTES": "Level of Assessment Reflecting Minimum Achievement equals 1"
  },
  {
    "SERIES": "SE_ADT_NMRCY",
    "FREQ": "A",
    "REFAREA": "JPN",
    "LOCATION": "T",
    "AGEGROUP": "016_050_Y",
    "SEX": "F",
    "TIMEPERIOD": "2012",
    "UNIT": "PERCENT",
    "UNITMULT": "0",
    "OBSVALUE": "98.7244011806",
    "NATURE": "C",
    "SOURCETYPE": "NA",
    "SOURCEDETAIL": "PIAAC (Programme for the International Assessment of Adult Competencies)",
    "TIMEDETAIL": "2012",
    "FOOTNOTES": "Level of Assessment Reflecting Minimum Achievement equals 1"
  },
  {
    "SERIES": "SE_ADT_NMRCY",
    "FREQ": "A",
    "REFAREA": "KOR",
    "LOCATION": "T",
    "AGEGROUP": "016_050_Y",
    "SEX": "F",
    "TIMEPERIOD": "2012",
    "UNIT": "PERCENT",
    "UNITMULT": "0",
    "OBSVALUE": "94.9299114031",
    "NATURE": "C",
    "SOURCETYPE": "NA",
    "SOURCEDETAIL": "PIAAC (Programme for the International Assessment of Adult Competencies)",
    "TIMEDETAIL": "2012",
    "FOOTNOTES": "Level of Assessment Reflecting Minimum Achievement equals 1"
  },
  {
    "SERIES": "SE_ADT_NMRCY",
    "FREQ": "A",
    "REFAREA": "NLD",
    "LOCATION": "T",
    "AGEGROUP": "016_050_Y",
    "SEX": "F",
    "TIMEPERIOD": "2012",
    "UNIT": "PERCENT",
    "UNITMULT": "0",
    "OBSVALUE": "95.8983713463",
    "NATURE": "C",
    "SOURCETYPE": "NA",
    "SOURCEDETAIL": "PIAAC (Programme for the International Assessment of Adult Competencies)",
    "TIMEDETAIL": "2012",
    "FOOTNOTES": "Level of Assessment Reflecting Minimum Achievement equals 1"
  },
  {
    "SERIES": "SE_ADT_NMRCY",
    "FREQ": "A",
    "REFAREA": "NOR",
    "LOCATION": "T",
    "AGEGROUP": "016_050_Y",
    "SEX": "F",
    "TIMEPERIOD": "2012",
    "UNIT": "PERCENT",
    "UNITMULT": "0",
    "OBSVALUE": "95.3597720494",
    "NATURE": "C",
    "SOURCETYPE": "NA",
    "SOURCEDETAIL": "PIAAC (Programme for the International Assessment of Adult Competencies)",
    "TIMEDETAIL": "2012",
    "FOOTNOTES": "Level of Assessment Reflecting Minimum Achievement equals 1"
  },
  {
    "SERIES": "SE_ADT_NMRCY",
    "FREQ": "A",
    "REFAREA": "POL",
    "LOCATION": "T",
    "AGEGROUP": "016_050_Y",
    "SEX": "F",
    "TIMEPERIOD": "2012",
    "UNIT": "PERCENT",
    "UNITMULT": "0",
    "OBSVALUE": "94.9435908589",
    "NATURE": "C",
    "SOURCETYPE": "NA",
    "SOURCEDETAIL": "PIAAC (Programme for the International Assessment of Adult Competencies)",
    "TIMEDETAIL": "2012",
    "FOOTNOTES": "Level of Assessment Reflecting Minimum Achievement equals 1"
  },
  {
    "SERIES": "SE_ADT_NMRCY",
    "FREQ": "A",
    "REFAREA": "SVK",
    "LOCATION": "T",
    "AGEGROUP": "016_050_Y",
    "SEX": "F",
    "TIMEPERIOD": "2012",
    "UNIT": "PERCENT",
    "UNITMULT": "0",
    "OBSVALUE": "96.353706136",
    "NATURE": "C",
    "SOURCETYPE": "NA",
    "SOURCEDETAIL": "PIAAC (Programme for the International Assessment of Adult Competencies)",
    "TIMEDETAIL": "2012",
    "FOOTNOTES": "Level of Assessment Reflecting Minimum Achievement equals 1"
  },
  {
    "SERIES": "SE_ADT_NMRCY",
    "FREQ": "A",
    "REFAREA": "SWE",
    "LOCATION": "T",
    "AGEGROUP": "016_050_Y",
    "SEX": "F",
    "TIMEPERIOD": "2012",
    "UNIT": "PERCENT",
    "UNITMULT": "0",
    "OBSVALUE": "94.6827021333",
    "NATURE": "C",
    "SOURCETYPE": "NA",
    "SOURCEDETAIL": "PIAAC (Programme for the International Assessment of Adult Competencies)",
    "TIMEDETAIL": "2012",
    "FOOTNOTES": "Level of Assessment Reflecting Minimum Achievement equals 1"
  },
  {
    "SERIES": "SE_ADT_NMRCY",
    "FREQ": "A",
    "REFAREA": "USA",
    "LOCATION": "T",
    "AGEGROUP": "016_050_Y",
    "SEX": "F",
    "TIMEPERIOD": "2012",
    "UNIT": "PERCENT",
    "UNITMULT": "0",
    "OBSVALUE": "89.2016425482",
    "NATURE": "C",
    "SOURCETYPE": "NA",
    "SOURCEDETAIL": "PIAAC (Programme for the International Assessment of Adult Competencies)",
    "TIMEDETAIL": "2012",
    "FOOTNOTES": "Level of Assessment Reflecting Minimum Achievement equals 1"
  },
  {
    "SERIES": "SE_ADT_NMRCY",
    "FREQ": "A",
    "REFAREA": "AUT",
    "LOCATION": "T",
    "AGEGROUP": "016_050_Y",
    "SEX": "M",
    "TIMEPERIOD": "2012",
    "UNIT": "PERCENT",
    "UNITMULT": "0",
    "OBSVALUE": "96.7400309058",
    "NATURE": "C",
    "SOURCETYPE": "NA",
    "SOURCEDETAIL": "PIAAC (Programme for the International Assessment of Adult Competencies)",
    "TIMEDETAIL": "2012",
    "FOOTNOTES": "Level of Assessment Reflecting Minimum Achievement equals 1"
  },
  {
    "SERIES": "SE_ADT_NMRCY",
    "FREQ": "A",
    "REFAREA": "BEL",
    "LOCATION": "T",
    "AGEGROUP": "016_050_Y",
    "SEX": "M",
    "TIMEPERIOD": "2012",
    "UNIT": "PERCENT",
    "UNITMULT": "0",
    "OBSVALUE": "97.1801626566",
    "NATURE": "C",
    "SOURCETYPE": "NA",
    "SOURCEDETAIL": "PIAAC (Programme for the International Assessment of Adult Competencies)",
    "TIMEDETAIL": "2012",
    "FOOTNOTES": "Level of Assessment Reflecting Minimum Achievement equals 1, Belgium (Flemish)"
  },
  {
    "SERIES": "SE_ADT_NMRCY",
    "FREQ": "A",
    "REFAREA": "CAN",
    "LOCATION": "T",
    "AGEGROUP": "016_050_Y",
    "SEX": "M",
    "TIMEPERIOD": "2012",
    "UNIT": "PERCENT",
    "UNITMULT": "0",
    "OBSVALUE": "94.9111208901",
    "NATURE": "C",
    "SOURCETYPE": "NA",
    "SOURCEDETAIL": "PIAAC (Programme for the International Assessment of Adult Competencies)",
    "TIMEDETAIL": "2012",
    "FOOTNOTES": "Level of Assessment Reflecting Minimum Achievement equals 1"
  },
  {
    "SERIES": "SE_ADT_NMRCY",
    "FREQ": "A",
    "REFAREA": "CZE",
    "LOCATION": "T",
    "AGEGROUP": "016_050_Y",
    "SEX": "M",
    "TIMEPERIOD": "2012",
    "UNIT": "PERCENT",
    "UNITMULT": "0",
    "OBSVALUE": "98.6095648588",
    "NATURE": "C",
    "SOURCETYPE": "NA",
    "SOURCEDETAIL": "PIAAC (Programme for the International Assessment of Adult Competencies)",
    "TIMEDETAIL": "2012",
    "FOOTNOTES": "Level of Assessment Reflecting Minimum Achievement equals 1"
  },
  {
    "SERIES": "SE_ADT_NMRCY",
    "FREQ": "A",
    "REFAREA": "DEU",
    "LOCATION": "T",
    "AGEGROUP": "016_050_Y",
    "SEX": "M",
    "TIMEPERIOD": "2012",
    "UNIT": "PERCENT",
    "UNITMULT": "0",
    "OBSVALUE": "96.6221194217",
    "NATURE": "C",
    "SOURCETYPE": "NA",
    "SOURCEDETAIL": "PIAAC (Programme for the International Assessment of Adult Competencies)",
    "TIMEDETAIL": "2012",
    "FOOTNOTES": "Level of Assessment Reflecting Minimum Achievement equals 1"
  },
  {
    "SERIES": "SE_ADT_NMRCY",
    "FREQ": "A",
    "REFAREA": "DNK",
    "LOCATION": "T",
    "AGEGROUP": "016_050_Y",
    "SEX": "M",
    "TIMEPERIOD": "2012",
    "UNIT": "PERCENT",
    "UNITMULT": "0",
    "OBSVALUE": "96.613603685",
    "NATURE": "C",
    "SOURCETYPE": "NA",
    "SOURCEDETAIL": "PIAAC (Programme for the International Assessment of Adult Competencies)",
    "TIMEDETAIL": "2012",
    "FOOTNOTES": "Level of Assessment Reflecting Minimum Achievement equals 1"
  },
  {
    "SERIES": "SE_ADT_NMRCY",
    "FREQ": "A",
    "REFAREA": "ESP",
    "LOCATION": "T",
    "AGEGROUP": "016_050_Y",
    "SEX": "M",
    "TIMEPERIOD": "2012",
    "UNIT": "PERCENT",
    "UNITMULT": "0",
    "OBSVALUE": "91.7165244617",
    "NATURE": "C",
    "SOURCETYPE": "NA",
    "SOURCEDETAIL": "PIAAC (Programme for the International Assessment of Adult Competencies)",
    "TIMEDETAIL": "2012",
    "FOOTNOTES": "Level of Assessment Reflecting Minimum Achievement equals 1"
  },
  {
    "SERIES": "SE_ADT_NMRCY",
    "FREQ": "A",
    "REFAREA": "EST",
    "LOCATION": "T",
    "AGEGROUP": "016_050_Y",
    "SEX": "M",
    "TIMEPERIOD": "2012",
    "UNIT": "PERCENT",
    "UNITMULT": "0",
    "OBSVALUE": "97.2814516371",
    "NATURE": "C",
    "SOURCETYPE": "NA",
    "SOURCEDETAIL": "PIAAC (Programme for the International Assessment of Adult Competencies)",
    "TIMEDETAIL": "2012",
    "FOOTNOTES": "Level of Assessment Reflecting Minimum Achievement equals 1"
  },
  {
    "SERIES": "SE_ADT_NMRCY",
    "FREQ": "A",
    "REFAREA": "FIN",
    "LOCATION": "T",
    "AGEGROUP": "016_050_Y",
    "SEX": "M",
    "TIMEPERIOD": "2012",
    "UNIT": "PERCENT",
    "UNITMULT": "0",
    "OBSVALUE": "96.9480851491",
    "NATURE": "C",
    "SOURCETYPE": "NA",
    "SOURCEDETAIL": "PIAAC (Programme for the International Assessment of Adult Competencies)",
    "TIMEDETAIL": "2012",
    "FOOTNOTES": "Level of Assessment Reflecting Minimum Achievement equals 1"
  },
  {
    "SERIES": "SE_ADT_NMRCY",
    "FREQ": "A",
    "REFAREA": "FRA",
    "LOCATION": "T",
    "AGEGROUP": "016_050_Y",
    "SEX": "M",
    "TIMEPERIOD": "2012",
    "UNIT": "PERCENT",
    "UNITMULT": "0",
    "OBSVALUE": "91.9543579355",
    "NATURE": "C",
    "SOURCETYPE": "NA",
    "SOURCEDETAIL": "PIAAC (Programme for the International Assessment of Adult Competencies)",
    "TIMEDETAIL": "2012",
    "FOOTNOTES": "Level of Assessment Reflecting Minimum Achievement equals 1"
  },
  {
    "SERIES": "SE_ADT_NMRCY",
    "FREQ": "A",
    "REFAREA": "GBR",
    "LOCATION": "T",
    "AGEGROUP": "016_050_Y",
    "SEX": "M",
    "TIMEPERIOD": "2012",
    "UNIT": "PERCENT",
    "UNITMULT": "0",
    "OBSVALUE": "94.4356267085",
    "NATURE": "C",
    "SOURCETYPE": "NA",
    "SOURCEDETAIL": "PIAAC (Programme for the International Assessment of Adult Competencies)",
    "TIMEDETAIL": "2012",
    "FOOTNOTES": "Level of Assessment Reflecting Minimum Achievement equals 1, UK comprises England and North Irland"
  },
  {
    "SERIES": "SE_ADT_NMRCY",
    "FREQ": "A",
    "REFAREA": "IRL",
    "LOCATION": "T",
    "AGEGROUP": "016_050_Y",
    "SEX": "M",
    "TIMEPERIOD": "2012",
    "UNIT": "PERCENT",
    "UNITMULT": "0",
    "OBSVALUE": "93.3669957095",
    "NATURE": "C",
    "SOURCETYPE": "NA",
    "SOURCEDETAIL": "PIAAC (Programme for the International Assessment of Adult Competencies)",
    "TIMEDETAIL": "2012",
    "FOOTNOTES": "Level of Assessment Reflecting Minimum Achievement equals 1"
  },
  {
    "SERIES": "SE_ADT_NMRCY",
    "FREQ": "A",
    "REFAREA": "ITA",
    "LOCATION": "T",
    "AGEGROUP": "016_050_Y",
    "SEX": "M",
    "TIMEPERIOD": "2012",
    "UNIT": "PERCENT",
    "UNITMULT": "0",
    "OBSVALUE": "92.9477264324",
    "NATURE": "C",
    "SOURCETYPE": "NA",
    "SOURCEDETAIL": "PIAAC (Programme for the International Assessment of Adult Competencies)",
    "TIMEDETAIL": "2012",
    "FOOTNOTES": "Level of Assessment Reflecting Minimum Achievement equals 1"
  },
  {
    "SERIES": "SE_ADT_NMRCY",
    "FREQ": "A",
    "REFAREA": "JPN",
    "LOCATION": "T",
    "AGEGROUP": "016_050_Y",
    "SEX": "M",
    "TIMEPERIOD": "2012",
    "UNIT": "PERCENT",
    "UNITMULT": "0",
    "OBSVALUE": "98.8919974579",
    "NATURE": "C",
    "SOURCETYPE": "NA",
    "SOURCEDETAIL": "PIAAC (Programme for the International Assessment of Adult Competencies)",
    "TIMEDETAIL": "2012",
    "FOOTNOTES": "Level of Assessment Reflecting Minimum Achievement equals 1"
  },
  {
    "SERIES": "SE_ADT_NMRCY",
    "FREQ": "A",
    "REFAREA": "KOR",
    "LOCATION": "T",
    "AGEGROUP": "016_050_Y",
    "SEX": "M",
    "TIMEPERIOD": "2012",
    "UNIT": "PERCENT",
    "UNITMULT": "0",
    "OBSVALUE": "96.694763051",
    "NATURE": "C",
    "SOURCETYPE": "NA",
    "SOURCEDETAIL": "PIAAC (Programme for the International Assessment of Adult Competencies)",
    "TIMEDETAIL": "2012",
    "FOOTNOTES": "Level of Assessment Reflecting Minimum Achievement equals 1"
  },
  {
    "SERIES": "SE_ADT_NMRCY",
    "FREQ": "A",
    "REFAREA": "NLD",
    "LOCATION": "T",
    "AGEGROUP": "016_050_Y",
    "SEX": "M",
    "TIMEPERIOD": "2012",
    "UNIT": "PERCENT",
    "UNITMULT": "0",
    "OBSVALUE": "96.9454955887",
    "NATURE": "C",
    "SOURCETYPE": "NA",
    "SOURCEDETAIL": "PIAAC (Programme for the International Assessment of Adult Competencies)",
    "TIMEDETAIL": "2012",
    "FOOTNOTES": "Level of Assessment Reflecting Minimum Achievement equals 1"
  },
  {
    "SERIES": "SE_ADT_NMRCY",
    "FREQ": "A",
    "REFAREA": "NOR",
    "LOCATION": "T",
    "AGEGROUP": "016_050_Y",
    "SEX": "M",
    "TIMEPERIOD": "2012",
    "UNIT": "PERCENT",
    "UNITMULT": "0",
    "OBSVALUE": "95.7564486361",
    "NATURE": "C",
    "SOURCETYPE": "NA",
    "SOURCEDETAIL": "PIAAC (Programme for the International Assessment of Adult Competencies)",
    "TIMEDETAIL": "2012",
    "FOOTNOTES": "Level of Assessment Reflecting Minimum Achievement equals 1"
  },
  {
    "SERIES": "SE_ADT_NMRCY",
    "FREQ": "A",
    "REFAREA": "POL",
    "LOCATION": "T",
    "AGEGROUP": "016_050_Y",
    "SEX": "M",
    "TIMEPERIOD": "2012",
    "UNIT": "PERCENT",
    "UNITMULT": "0",
    "OBSVALUE": "93.2054916703",
    "NATURE": "C",
    "SOURCETYPE": "NA",
    "SOURCEDETAIL": "PIAAC (Programme for the International Assessment of Adult Competencies)",
    "TIMEDETAIL": "2012",
    "FOOTNOTES": "Level of Assessment Reflecting Minimum Achievement equals 1"
  },
  {
    "SERIES": "SE_ADT_NMRCY",
    "FREQ": "A",
    "REFAREA": "SVK",
    "LOCATION": "T",
    "AGEGROUP": "016_050_Y",
    "SEX": "M",
    "TIMEPERIOD": "2012",
    "UNIT": "PERCENT",
    "UNITMULT": "0",
    "OBSVALUE": "96.7201366351",
    "NATURE": "C",
    "SOURCETYPE": "NA",
    "SOURCEDETAIL": "PIAAC (Programme for the International Assessment of Adult Competencies)",
    "TIMEDETAIL": "2012",
    "FOOTNOTES": "Level of Assessment Reflecting Minimum Achievement equals 1"
  },
  {
    "SERIES": "SE_ADT_NMRCY",
    "FREQ": "A",
    "REFAREA": "SWE",
    "LOCATION": "T",
    "AGEGROUP": "016_050_Y",
    "SEX": "M",
    "TIMEPERIOD": "2012",
    "UNIT": "PERCENT",
    "UNITMULT": "0",
    "OBSVALUE": "96.51984406",
    "NATURE": "C",
    "SOURCETYPE": "NA",
    "SOURCEDETAIL": "PIAAC (Programme for the International Assessment of Adult Competencies)",
    "TIMEDETAIL": "2012",
    "FOOTNOTES": "Level of Assessment Reflecting Minimum Achievement equals 1"
  },
  {
    "SERIES": "SE_ADT_NMRCY",
    "FREQ": "A",
    "REFAREA": "USA",
    "LOCATION": "T",
    "AGEGROUP": "016_050_Y",
    "SEX": "M",
    "TIMEPERIOD": "2012",
    "UNIT": "PERCENT",
    "UNITMULT": "0",
    "OBSVALUE": "91.8488776528",
    "NATURE": "C",
    "SOURCETYPE": "NA",
    "SOURCEDETAIL": "PIAAC (Programme for the International Assessment of Adult Competencies)",
    "TIMEDETAIL": "2012",
    "FOOTNOTES": "Level of Assessment Reflecting Minimum Achievement equals 1"
  },
  {
    "SERIES": "SE_ADT_NMRCY",
    "FREQ": "A",
    "REFAREA": "AUS",
    "LOCATION": "T",
    "AGEGROUP": "016_050_Y",
    "SEX": "T",
    "TIMEPERIOD": "2012",
    "UNIT": "PERCENT",
    "UNITMULT": "0",
    "OBSVALUE": "94.1590316844",
    "NATURE": "C",
    "SOURCETYPE": "NA",
    "SOURCEDETAIL": "PIAAC (Programme for the International Assessment of Adult Competencies)",
    "TIMEDETAIL": "2012",
    "FOOTNOTES": "Level of Assessment Reflecting Minimum Achievement equals 1"
  },
  {
    "SERIES": "SE_ADT_NMRCY",
    "FREQ": "A",
    "REFAREA": "AUT",
    "LOCATION": "T",
    "AGEGROUP": "016_050_Y",
    "SEX": "T",
    "TIMEPERIOD": "2012",
    "UNIT": "PERCENT",
    "UNITMULT": "0",
    "OBSVALUE": "96.5352224479",
    "NATURE": "C",
    "SOURCETYPE": "NA",
    "SOURCEDETAIL": "PIAAC (Programme for the International Assessment of Adult Competencies)",
    "TIMEDETAIL": "2012",
    "FOOTNOTES": "Level of Assessment Reflecting Minimum Achievement equals 1"
  },
  {
    "SERIES": "SE_ADT_NMRCY",
    "FREQ": "A",
    "REFAREA": "BEL",
    "LOCATION": "T",
    "AGEGROUP": "016_050_Y",
    "SEX": "T",
    "TIMEPERIOD": "2012",
    "UNIT": "PERCENT",
    "UNITMULT": "0",
    "OBSVALUE": "96.8869137701",
    "NATURE": "C",
    "SOURCETYPE": "NA",
    "SOURCEDETAIL": "PIAAC (Programme for the International Assessment of Adult Competencies)",
    "TIMEDETAIL": "2012",
    "FOOTNOTES": "Level of Assessment Reflecting Minimum Achievement equals 1, Belgium (Flemish)"
  },
  {
    "SERIES": "SE_ADT_NMRCY",
    "FREQ": "A",
    "REFAREA": "CAN",
    "LOCATION": "T",
    "AGEGROUP": "016_050_Y",
    "SEX": "T",
    "TIMEPERIOD": "2012",
    "UNIT": "PERCENT",
    "UNITMULT": "0",
    "OBSVALUE": "94.0402360715",
    "NATURE": "C",
    "SOURCETYPE": "NA",
    "SOURCEDETAIL": "PIAAC (Programme for the International Assessment of Adult Competencies)",
    "TIMEDETAIL": "2012",
    "FOOTNOTES": "Level of Assessment Reflecting Minimum Achievement equals 1"
  },
  {
    "SERIES": "SE_ADT_NMRCY",
    "FREQ": "A",
    "REFAREA": "CYP",
    "LOCATION": "T",
    "AGEGROUP": "016_050_Y",
    "SEX": "T",
    "TIMEPERIOD": "2012",
    "UNIT": "PERCENT",
    "UNITMULT": "0",
    "OBSVALUE": "95.8981325427",
    "NATURE": "C",
    "SOURCETYPE": "NA",
    "SOURCEDETAIL": "PIAAC (Programme for the International Assessment of Adult Competencies)",
    "TIMEDETAIL": "2012",
    "FOOTNOTES": "Level of Assessment Reflecting Minimum Achievement equals 1"
  },
  {
    "SERIES": "SE_ADT_NMRCY",
    "FREQ": "A",
    "REFAREA": "CZE",
    "LOCATION": "T",
    "AGEGROUP": "016_050_Y",
    "SEX": "T",
    "TIMEPERIOD": "2012",
    "UNIT": "PERCENT",
    "UNITMULT": "0",
    "OBSVALUE": "98.2540437003",
    "NATURE": "C",
    "SOURCETYPE": "NA",
    "SOURCEDETAIL": "PIAAC (Programme for the International Assessment of Adult Competencies)",
    "TIMEDETAIL": "2012",
    "FOOTNOTES": "Level of Assessment Reflecting Minimum Achievement equals 1"
  },
  {
    "SERIES": "SE_ADT_NMRCY",
    "FREQ": "A",
    "REFAREA": "DEU",
    "LOCATION": "T",
    "AGEGROUP": "016_050_Y",
    "SEX": "T",
    "TIMEPERIOD": "2012",
    "UNIT": "PERCENT",
    "UNITMULT": "0",
    "OBSVALUE": "95.4243478951",
    "NATURE": "C",
    "SOURCETYPE": "NA",
    "SOURCEDETAIL": "PIAAC (Programme for the International Assessment of Adult Competencies)",
    "TIMEDETAIL": "2012",
    "FOOTNOTES": "Level of Assessment Reflecting Minimum Achievement equals 1"
  },
  {
    "SERIES": "SE_ADT_NMRCY",
    "FREQ": "A",
    "REFAREA": "DNK",
    "LOCATION": "T",
    "AGEGROUP": "016_050_Y",
    "SEX": "T",
    "TIMEPERIOD": "2012",
    "UNIT": "PERCENT",
    "UNITMULT": "0",
    "OBSVALUE": "96.5775709375",
    "NATURE": "C",
    "SOURCETYPE": "NA",
    "SOURCEDETAIL": "PIAAC (Programme for the International Assessment of Adult Competencies)",
    "TIMEDETAIL": "2012",
    "FOOTNOTES": "Level of Assessment Reflecting Minimum Achievement equals 1"
  },
  {
    "SERIES": "SE_ADT_NMRCY",
    "FREQ": "A",
    "REFAREA": "ESP",
    "LOCATION": "T",
    "AGEGROUP": "016_050_Y",
    "SEX": "T",
    "TIMEPERIOD": "2012",
    "UNIT": "PERCENT",
    "UNITMULT": "0",
    "OBSVALUE": "90.3976991913",
    "NATURE": "C",
    "SOURCETYPE": "NA",
    "SOURCEDETAIL": "PIAAC (Programme for the International Assessment of Adult Competencies)",
    "TIMEDETAIL": "2012",
    "FOOTNOTES": "Level of Assessment Reflecting Minimum Achievement equals 1"
  },
  {
    "SERIES": "SE_ADT_NMRCY",
    "FREQ": "A",
    "REFAREA": "EST",
    "LOCATION": "T",
    "AGEGROUP": "016_050_Y",
    "SEX": "T",
    "TIMEPERIOD": "2012",
    "UNIT": "PERCENT",
    "UNITMULT": "0",
    "OBSVALUE": "97.5802027236",
    "NATURE": "C",
    "SOURCETYPE": "NA",
    "SOURCEDETAIL": "PIAAC (Programme for the International Assessment of Adult Competencies)",
    "TIMEDETAIL": "2012",
    "FOOTNOTES": "Level of Assessment Reflecting Minimum Achievement equals 1"
  },
  {
    "SERIES": "SE_ADT_NMRCY",
    "FREQ": "A",
    "REFAREA": "FIN",
    "LOCATION": "T",
    "AGEGROUP": "016_050_Y",
    "SEX": "T",
    "TIMEPERIOD": "2012",
    "UNIT": "PERCENT",
    "UNITMULT": "0",
    "OBSVALUE": "96.8822118532",
    "NATURE": "C",
    "SOURCETYPE": "NA",
    "SOURCEDETAIL": "PIAAC (Programme for the International Assessment of Adult Competencies)",
    "TIMEDETAIL": "2012",
    "FOOTNOTES": "Level of Assessment Reflecting Minimum Achievement equals 1"
  },
  {
    "SERIES": "SE_ADT_NMRCY",
    "FREQ": "A",
    "REFAREA": "FRA",
    "LOCATION": "T",
    "AGEGROUP": "016_050_Y",
    "SEX": "T",
    "TIMEPERIOD": "2012",
    "UNIT": "PERCENT",
    "UNITMULT": "0",
    "OBSVALUE": "90.8394562774",
    "NATURE": "C",
    "SOURCETYPE": "NA",
    "SOURCEDETAIL": "PIAAC (Programme for the International Assessment of Adult Competencies)",
    "TIMEDETAIL": "2012",
    "FOOTNOTES": "Level of Assessment Reflecting Minimum Achievement equals 1"
  },
  {
    "SERIES": "SE_ADT_NMRCY",
    "FREQ": "A",
    "REFAREA": "GBR",
    "LOCATION": "T",
    "AGEGROUP": "016_050_Y",
    "SEX": "T",
    "TIMEPERIOD": "2012",
    "UNIT": "PERCENT",
    "UNITMULT": "0",
    "OBSVALUE": "93.5719514619",
    "NATURE": "C",
    "SOURCETYPE": "NA",
    "SOURCEDETAIL": "PIAAC (Programme for the International Assessment of Adult Competencies)",
    "TIMEDETAIL": "2012",
    "FOOTNOTES": "Level of Assessment Reflecting Minimum Achievement equals 1, UK comprises England and North Irland"
  },
  {
    "SERIES": "SE_ADT_NMRCY",
    "FREQ": "A",
    "REFAREA": "IRL",
    "LOCATION": "T",
    "AGEGROUP": "016_050_Y",
    "SEX": "T",
    "TIMEPERIOD": "2012",
    "UNIT": "PERCENT",
    "UNITMULT": "0",
    "OBSVALUE": "92.8810322803",
    "NATURE": "C",
    "SOURCETYPE": "NA",
    "SOURCEDETAIL": "PIAAC (Programme for the International Assessment of Adult Competencies)",
    "TIMEDETAIL": "2012",
    "FOOTNOTES": "Level of Assessment Reflecting Minimum Achievement equals 1"
  },
  {
    "SERIES": "SE_ADT_NMRCY",
    "FREQ": "A",
    "REFAREA": "ITA",
    "LOCATION": "T",
    "AGEGROUP": "016_050_Y",
    "SEX": "T",
    "TIMEPERIOD": "2012",
    "UNIT": "PERCENT",
    "UNITMULT": "0",
    "OBSVALUE": "91.9",
    "NATURE": "C",
    "SOURCETYPE": "NA",
    "SOURCEDETAIL": "PIAAC (Programme for the International Assessment of Adult Competencies)",
    "TIMEDETAIL": "2012",
    "FOOTNOTES": "Level of Assessment Reflecting Minimum Achievement equals 1"
  },
  {
    "SERIES": "SE_ADT_NMRCY",
    "FREQ": "A",
    "REFAREA": "JPN",
    "LOCATION": "T",
    "AGEGROUP": "016_050_Y",
    "SEX": "T",
    "TIMEPERIOD": "2012",
    "UNIT": "PERCENT",
    "UNITMULT": "0",
    "OBSVALUE": "98.808654475",
    "NATURE": "C",
    "SOURCETYPE": "NA",
    "SOURCEDETAIL": "PIAAC (Programme for the International Assessment of Adult Competencies)",
    "TIMEDETAIL": "2012",
    "FOOTNOTES": "Level of Assessment Reflecting Minimum Achievement equals 1"
  },
  {
    "SERIES": "SE_ADT_NMRCY",
    "FREQ": "A",
    "REFAREA": "KOR",
    "LOCATION": "T",
    "AGEGROUP": "016_050_Y",
    "SEX": "T",
    "TIMEPERIOD": "2012",
    "UNIT": "PERCENT",
    "UNITMULT": "0",
    "OBSVALUE": "95.8078463231",
    "NATURE": "C",
    "SOURCETYPE": "NA",
    "SOURCEDETAIL": "PIAAC (Programme for the International Assessment of Adult Competencies)",
    "TIMEDETAIL": "2012",
    "FOOTNOTES": "Level of Assessment Reflecting Minimum Achievement equals 1"
  },
  {
    "SERIES": "SE_ADT_NMRCY",
    "FREQ": "A",
    "REFAREA": "NLD",
    "LOCATION": "T",
    "AGEGROUP": "016_050_Y",
    "SEX": "T",
    "TIMEPERIOD": "2012",
    "UNIT": "PERCENT",
    "UNITMULT": "0",
    "OBSVALUE": "96.4246099731",
    "NATURE": "C",
    "SOURCETYPE": "NA",
    "SOURCEDETAIL": "PIAAC (Programme for the International Assessment of Adult Competencies)",
    "TIMEDETAIL": "2012",
    "FOOTNOTES": "Level of Assessment Reflecting Minimum Achievement equals 1"
  },
  {
    "SERIES": "SE_ADT_NMRCY",
    "FREQ": "A",
    "REFAREA": "NOR",
    "LOCATION": "T",
    "AGEGROUP": "016_050_Y",
    "SEX": "T",
    "TIMEPERIOD": "2012",
    "UNIT": "PERCENT",
    "UNITMULT": "0",
    "OBSVALUE": "95.5624343692",
    "NATURE": "C",
    "SOURCETYPE": "NA",
    "SOURCEDETAIL": "PIAAC (Programme for the International Assessment of Adult Competencies)",
    "TIMEDETAIL": "2012",
    "FOOTNOTES": "Level of Assessment Reflecting Minimum Achievement equals 1"
  },
  {
    "SERIES": "SE_ADT_NMRCY",
    "FREQ": "A",
    "REFAREA": "POL",
    "LOCATION": "T",
    "AGEGROUP": "016_050_Y",
    "SEX": "T",
    "TIMEPERIOD": "2012",
    "UNIT": "PERCENT",
    "UNITMULT": "0",
    "OBSVALUE": "94.083768177",
    "NATURE": "C",
    "SOURCETYPE": "NA",
    "SOURCEDETAIL": "PIAAC (Programme for the International Assessment of Adult Competencies)",
    "TIMEDETAIL": "2012",
    "FOOTNOTES": "Level of Assessment Reflecting Minimum Achievement equals 1"
  },
  {
    "SERIES": "SE_ADT_NMRCY",
    "FREQ": "A",
    "REFAREA": "SVK",
    "LOCATION": "T",
    "AGEGROUP": "016_050_Y",
    "SEX": "T",
    "TIMEPERIOD": "2012",
    "UNIT": "PERCENT",
    "UNITMULT": "0",
    "OBSVALUE": "96.5368701158",
    "NATURE": "C",
    "SOURCETYPE": "NA",
    "SOURCEDETAIL": "PIAAC (Programme for the International Assessment of Adult Competencies)",
    "TIMEDETAIL": "2012",
    "FOOTNOTES": "Level of Assessment Reflecting Minimum Achievement equals 1"
  },
  {
    "SERIES": "SE_ADT_NMRCY",
    "FREQ": "A",
    "REFAREA": "SWE",
    "LOCATION": "T",
    "AGEGROUP": "016_050_Y",
    "SEX": "T",
    "TIMEPERIOD": "2012",
    "UNIT": "PERCENT",
    "UNITMULT": "0",
    "OBSVALUE": "95.6147607642",
    "NATURE": "C",
    "SOURCETYPE": "NA",
    "SOURCEDETAIL": "PIAAC (Programme for the International Assessment of Adult Competencies)",
    "TIMEDETAIL": "2012",
    "FOOTNOTES": "Level of Assessment Reflecting Minimum Achievement equals 1"
  },
  {
    "SERIES": "SE_ADT_NMRCY",
    "FREQ": "A",
    "REFAREA": "USA",
    "LOCATION": "T",
    "AGEGROUP": "016_050_Y",
    "SEX": "T",
    "TIMEPERIOD": "2012",
    "UNIT": "PERCENT",
    "UNITMULT": "0",
    "OBSVALUE": "90.4939911686",
    "NATURE": "C",
    "SOURCETYPE": "NA",
    "SOURCEDETAIL": "PIAAC (Programme for the International Assessment of Adult Competencies)",
    "TIMEDETAIL": "2012",
    "FOOTNOTES": "Level of Assessment Reflecting Minimum Achievement equals 1"
  }
]