[
  {
    "SERIES": "ER_HYG_PARTIC",
    "FREQ": "A",
    "REFAREA": "CAU_CEN_ASIA",
    "LOCATION": "T",
    "AGEGROUP": "000_099_Y",
    "SEX": "T",
    "TIMEPERIOD": "2014",
    "UNIT": "PERCENT",
    "UNITMULT": "0",
    "OBSVALUE": "20",
    "NATURE": "NA",
    "SOURCETYPE": "NA",
    "SOURCEDETAIL": null,
    "TIMEDETAIL": "2012 - 2014",
    "FOOTNOTES": null
  },
  {
    "SERIES": "ER_HYG_PARTIC",
    "FREQ": "A",
    "REFAREA": "MDG_DEVELOPED_REG",
    "LOCATION": "T",
    "AGEGROUP": "000_099_Y",
    "SEX": "T",
    "TIMEPERIOD": "2014",
    "UNIT": "PERCENT",
    "UNITMULT": "0",
    "OBSVALUE": "0",
    "NATURE": "NA",
    "SOURCETYPE": "NA",
    "SOURCEDETAIL": null,
    "TIMEDETAIL": "2012 - 2014",
    "FOOTNOTES": null
  },
  {
    "SERIES": "ER_HYG_PARTIC",
    "FREQ": "A",
    "REFAREA": "MDG_DEVELOPING_REG",
    "LOCATION": "T",
    "AGEGROUP": "000_099_Y",
    "SEX": "T",
    "TIMEPERIOD": "2014",
    "UNIT": "PERCENT",
    "UNITMULT": "0",
    "OBSVALUE": "17.8",
    "NATURE": "NA",
    "SOURCETYPE": "NA",
    "SOURCEDETAIL": null,
    "TIMEDETAIL": "2012 - 2014",
    "FOOTNOTES": null
  },
  {
    "SERIES": "ER_HYG_PARTIC",
    "FREQ": "A",
    "REFAREA": "MDG_EAS",
    "LOCATION": "T",
    "AGEGROUP": "000_099_Y",
    "SEX": "T",
    "TIMEPERIOD": "2014",
    "UNIT": "PERCENT",
    "UNITMULT": "0",
    "OBSVALUE": "0",
    "NATURE": "NA",
    "SOURCETYPE": "NA",
    "SOURCEDETAIL": null,
    "TIMEDETAIL": "2012 - 2014",
    "FOOTNOTES": null
  },
  {
    "SERIES": "ER_HYG_PARTIC",
    "FREQ": "A",
    "REFAREA": "MDG_EAS_NOCHINA",
    "LOCATION": "T",
    "AGEGROUP": "000_099_Y",
    "SEX": "T",
    "TIMEPERIOD": "2014",
    "UNIT": "PERCENT",
    "UNITMULT": "0",
    "OBSVALUE": "0",
    "NATURE": "NA",
    "SOURCETYPE": "NA",
    "SOURCEDETAIL": null,
    "TIMEDETAIL": "2012 - 2014",
    "FOOTNOTES": null
  },
  {
    "SERIES": "ER_HYG_PARTIC",
    "FREQ": "A",
    "REFAREA": "MDG_LAC",
    "LOCATION": "T",
    "AGEGROUP": "000_099_Y",
    "SEX": "T",
    "TIMEPERIOD": "2014",
    "UNIT": "PERCENT",
    "UNITMULT": "0",
    "OBSVALUE": "18.8",
    "NATURE": "NA",
    "SOURCETYPE": "NA",
    "SOURCEDETAIL": null,
    "TIMEDETAIL": "2012 - 2014",
    "FOOTNOTES": null
  },
  {
    "SERIES": "ER_HYG_PARTIC",
    "FREQ": "A",
    "REFAREA": "MDG_LDC",
    "LOCATION": "T",
    "AGEGROUP": "000_099_Y",
    "SEX": "T",
    "TIMEPERIOD": "2014",
    "UNIT": "PERCENT",
    "UNITMULT": "0",
    "OBSVALUE": "17.6",
    "NATURE": "NA",
    "SOURCETYPE": "NA",
    "SOURCEDETAIL": null,
    "TIMEDETAIL": "2012 - 2014",
    "FOOTNOTES": null
  },
  {
    "SERIES": "ER_HYG_PARTIC",
    "FREQ": "A",
    "REFAREA": "MDG_LLDC",
    "LOCATION": "T",
    "AGEGROUP": "000_099_Y",
    "SEX": "T",
    "TIMEPERIOD": "2014",
    "UNIT": "PERCENT",
    "UNITMULT": "0",
    "OBSVALUE": "16.7",
    "NATURE": "NA",
    "SOURCETYPE": "NA",
    "SOURCEDETAIL": null,
    "TIMEDETAIL": "2012 - 2014",
    "FOOTNOTES": null
  },
  {
    "SERIES": "ER_HYG_PARTIC",
    "FREQ": "A",
    "REFAREA": "MDG_NAFR",
    "LOCATION": "T",
    "AGEGROUP": "000_099_Y",
    "SEX": "T",
    "TIMEPERIOD": "2014",
    "UNIT": "PERCENT",
    "UNITMULT": "0",
    "OBSVALUE": "0",
    "NATURE": "NA",
    "SOURCETYPE": "NA",
    "SOURCEDETAIL": null,
    "TIMEDETAIL": "2012 - 2014",
    "FOOTNOTES": null
  },
  {
    "SERIES": "ER_HYG_PARTIC",
    "FREQ": "A",
    "REFAREA": "MDG_OCE",
    "LOCATION": "T",
    "AGEGROUP": "000_099_Y",
    "SEX": "T",
    "TIMEPERIOD": "2014",
    "UNIT": "PERCENT",
    "UNITMULT": "0",
    "OBSVALUE": "50",
    "NATURE": "NA",
    "SOURCETYPE": "NA",
    "SOURCEDETAIL": null,
    "TIMEDETAIL": "2012 - 2014",
    "FOOTNOTES": null
  },
  {
    "SERIES": "ER_HYG_PARTIC",
    "FREQ": "A",
    "REFAREA": "MDG_SAS",
    "LOCATION": "T",
    "AGEGROUP": "000_099_Y",
    "SEX": "T",
    "TIMEPERIOD": "2014",
    "UNIT": "PERCENT",
    "UNITMULT": "0",
    "OBSVALUE": "22.2",
    "NATURE": "NA",
    "SOURCETYPE": "NA",
    "SOURCEDETAIL": null,
    "TIMEDETAIL": "2012 - 2014",
    "FOOTNOTES": null
  },
  {
    "SERIES": "ER_HYG_PARTIC",
    "FREQ": "A",
    "REFAREA": "MDG_SAS_NOINDIA",
    "LOCATION": "T",
    "AGEGROUP": "000_099_Y",
    "SEX": "T",
    "TIMEPERIOD": "2014",
    "UNIT": "PERCENT",
    "UNITMULT": "0",
    "OBSVALUE": "25",
    "NATURE": "NA",
    "SOURCETYPE": "NA",
    "SOURCEDETAIL": null,
    "TIMEDETAIL": "2012 - 2014",
    "FOOTNOTES": null
  },
  {
    "SERIES": "ER_HYG_PARTIC",
    "FREQ": "A",
    "REFAREA": "MDG_SEAS",
    "LOCATION": "T",
    "AGEGROUP": "000_099_Y",
    "SEX": "T",
    "TIMEPERIOD": "2014",
    "UNIT": "PERCENT",
    "UNITMULT": "0",
    "OBSVALUE": "25",
    "NATURE": "NA",
    "SOURCETYPE": "NA",
    "SOURCEDETAIL": null,
    "TIMEDETAIL": "2012 - 2014",
    "FOOTNOTES": null
  },
  {
    "SERIES": "ER_HYG_PARTIC",
    "FREQ": "A",
    "REFAREA": "MDG_SIDS",
    "LOCATION": "T",
    "AGEGROUP": "000_099_Y",
    "SEX": "T",
    "TIMEPERIOD": "2014",
    "UNIT": "PERCENT",
    "UNITMULT": "0",
    "OBSVALUE": "42.9",
    "NATURE": "NA",
    "SOURCETYPE": "NA",
    "SOURCEDETAIL": null,
    "TIMEDETAIL": "2012 - 2014",
    "FOOTNOTES": null
  },
  {
    "SERIES": "ER_HYG_PARTIC",
    "FREQ": "A",
    "REFAREA": "MDG_SSA",
    "LOCATION": "T",
    "AGEGROUP": "000_099_Y",
    "SEX": "T",
    "TIMEPERIOD": "2014",
    "UNIT": "PERCENT",
    "UNITMULT": "0",
    "OBSVALUE": "8.1",
    "NATURE": "NA",
    "SOURCETYPE": "NA",
    "SOURCEDETAIL": null,
    "TIMEDETAIL": "2012 - 2014",
    "FOOTNOTES": null
  },
  {
    "SERIES": "ER_HYG_PARTIC",
    "FREQ": "A",
    "REFAREA": "MDG_WEST_AS",
    "LOCATION": "T",
    "AGEGROUP": "000_099_Y",
    "SEX": "T",
    "TIMEPERIOD": "2014",
    "UNIT": "PERCENT",
    "UNITMULT": "0",
    "OBSVALUE": "0",
    "NATURE": "NA",
    "SOURCETYPE": "NA",
    "SOURCEDETAIL": null,
    "TIMEDETAIL": "2012 - 2014",
    "FOOTNOTES": null
  },
  {
    "SERIES": "ER_HYG_PARTIC",
    "FREQ": "A",
    "REFAREA": "MDG_WORLD",
    "LOCATION": "T",
    "AGEGROUP": "000_099_Y",
    "SEX": "T",
    "TIMEPERIOD": "2014",
    "UNIT": "PERCENT",
    "UNITMULT": "0",
    "OBSVALUE": "13.8",
    "NATURE": "NA",
    "SOURCETYPE": "NA",
    "SOURCEDETAIL": null,
    "TIMEDETAIL": "2012 - 2014",
    "FOOTNOTES": null
  }
]