[
               # Replace Windows newlines with Unix  {
               # Replace Windows newlines with Unix    "SERIES": "SE_SEC_TRTCHRTCH",
               # Replace Windows newlines with Unix    "FREQ": "A",
               # Replace Windows newlines with Unix    "REFAREA": "CAU_CEN_ASIA",
               # Replace Windows newlines with Unix    "LOCATION": "T",
               # Replace Windows newlines with Unix    "AGEGROUP": "000_099_Y",
               # Replace Windows newlines with Unix    "SEX": "F",
               # Replace Windows newlines with Unix    "TIMEPERIOD": "2005",
               # Replace Windows newlines with Unix    "UNIT": "PERCENT",
               # Replace Windows newlines with Unix    "UNITMULT": "0",
               # Replace Windows newlines with Unix    "OBSVALUE": "97",
               # Replace Windows newlines with Unix    "NATURE": "NA",
               # Replace Windows newlines with Unix    "SOURCETYPE": "NA",
               # Replace Windows newlines with Unix    "SOURCEDETAIL": null,
               # Replace Windows newlines with Unix    "TIMEDETAIL": "2005",
               # Replace Windows newlines with Unix    "FOOTNOTES": null
               # Replace Windows newlines with Unix  },
               # Replace Windows newlines with Unix  {
               # Replace Windows newlines with Unix    "SERIES": "SE_SEC_TRTCHRTCH",
               # Replace Windows newlines with Unix    "FREQ": "A",
               # Replace Windows newlines with Unix    "REFAREA": "CAU_CEN_ASIA",
               # Replace Windows newlines with Unix    "LOCATION": "T",
               # Replace Windows newlines with Unix    "AGEGROUP": "000_099_Y",
               # Replace Windows newlines with Unix    "SEX": "F",
               # Replace Windows newlines with Unix    "TIMEPERIOD": "2010",
               # Replace Windows newlines with Unix    "UNIT": "PERCENT",
               # Replace Windows newlines with Unix    "UNITMULT": "0",
               # Replace Windows newlines with Unix    "OBSVALUE": "96",
               # Replace Windows newlines with Unix    "NATURE": "NA",
               # Replace Windows newlines with Unix    "SOURCETYPE": "NA",
               # Replace Windows newlines with Unix    "SOURCEDETAIL": null,
               # Replace Windows newlines with Unix    "TIMEDETAIL": "2010",
               # Replace Windows newlines with Unix    "FOOTNOTES": null
               # Replace Windows newlines with Unix  },
               # Replace Windows newlines with Unix  {
               # Replace Windows newlines with Unix    "SERIES": "SE_SEC_TRTCHRTCH",
               # Replace Windows newlines with Unix    "FREQ": "A",
               # Replace Windows newlines with Unix    "REFAREA": "CAU_CEN_ASIA",
               # Replace Windows newlines with Unix    "LOCATION": "T",
               # Replace Windows newlines with Unix    "AGEGROUP": "000_099_Y",
               # Replace Windows newlines with Unix    "SEX": "F",
               # Replace Windows newlines with Unix    "TIMEPERIOD": "2012",
               # Replace Windows newlines with Unix    "UNIT": "PERCENT",
               # Replace Windows newlines with Unix    "UNITMULT": "0",
               # Replace Windows newlines with Unix    "OBSVALUE": "94",
               # Replace Windows newlines with Unix    "NATURE": "NA",
               # Replace Windows newlines with Unix    "SOURCETYPE": "NA",
               # Replace Windows newlines with Unix    "SOURCEDETAIL": null,
               # Replace Windows newlines with Unix    "TIMEDETAIL": "2012",
               # Replace Windows newlines with Unix    "FOOTNOTES": null
               # Replace Windows newlines with Unix  },
               # Replace Windows newlines with Unix  {
               # Replace Windows newlines with Unix    "SERIES": "SE_SEC_TRTCHRTCH",
               # Replace Windows newlines with Unix    "FREQ": "A",
               # Replace Windows newlines with Unix    "REFAREA": "MDG_LDC",
               # Replace Windows newlines with Unix    "LOCATION": "T",
               # Replace Windows newlines with Unix    "AGEGROUP": "000_099_Y",
               # Replace Windows newlines with Unix    "SEX": "F",
               # Replace Windows newlines with Unix    "TIMEPERIOD": "2000",
               # Replace Windows newlines with Unix    "UNIT": "PERCENT",
               # Replace Windows newlines with Unix    "UNITMULT": "0",
               # Replace Windows newlines with Unix    "OBSVALUE": "73",
               # Replace Windows newlines with Unix    "NATURE": "NA",
               # Replace Windows newlines with Unix    "SOURCETYPE": "NA",
               # Replace Windows newlines with Unix    "SOURCEDETAIL": null,
               # Replace Windows newlines with Unix    "TIMEDETAIL": "2000",
               # Replace Windows newlines with Unix    "FOOTNOTES": null
               # Replace Windows newlines with Unix  },
               # Replace Windows newlines with Unix  {
               # Replace Windows newlines with Unix    "SERIES": "SE_SEC_TRTCHRTCH",
               # Replace Windows newlines with Unix    "FREQ": "A",
               # Replace Windows newlines with Unix    "REFAREA": "MDG_LDC",
               # Replace Windows newlines with Unix    "LOCATION": "T",
               # Replace Windows newlines with Unix    "AGEGROUP": "000_099_Y",
               # Replace Windows newlines with Unix    "SEX": "F",
               # Replace Windows newlines with Unix    "TIMEPERIOD": "2005",
               # Replace Windows newlines with Unix    "UNIT": "PERCENT",
               # Replace Windows newlines with Unix    "UNITMULT": "0",
               # Replace Windows newlines with Unix    "OBSVALUE": "68",
               # Replace Windows newlines with Unix    "NATURE": "NA",
               # Replace Windows newlines with Unix    "SOURCETYPE": "NA",
               # Replace Windows newlines with Unix    "SOURCEDETAIL": null,
               # Replace Windows newlines with Unix    "TIMEDETAIL": "2005",
               # Replace Windows newlines with Unix    "FOOTNOTES": null
               # Replace Windows newlines with Unix  },
               # Replace Windows newlines with Unix  {
               # Replace Windows newlines with Unix    "SERIES": "SE_SEC_TRTCHRTCH",
               # Replace Windows newlines with Unix    "FREQ": "A",
               # Replace Windows newlines with Unix    "REFAREA": "MDG_LDC",
               # Replace Windows newlines with Unix    "LOCATION": "T",
               # Replace Windows newlines with Unix    "AGEGROUP": "000_099_Y",
               # Replace Windows newlines with Unix    "SEX": "F",
               # Replace Windows newlines with Unix    "TIMEPERIOD": "2010",
               # Replace Windows newlines with Unix    "UNIT": "PERCENT",
               # Replace Windows newlines with Unix    "UNITMULT": "0",
               # Replace Windows newlines with Unix    "OBSVALUE": "68",
               # Replace Windows newlines with Unix    "NATURE": "NA",
               # Replace Windows newlines with Unix    "SOURCETYPE": "NA",
               # Replace Windows newlines with Unix    "SOURCEDETAIL": null,
               # Replace Windows newlines with Unix    "TIMEDETAIL": "2010",
               # Replace Windows newlines with Unix    "FOOTNOTES": null
               # Replace Windows newlines with Unix  },
               # Replace Windows newlines with Unix  {
               # Replace Windows newlines with Unix    "SERIES": "SE_SEC_TRTCHRTCH",
               # Replace Windows newlines with Unix    "FREQ": "A",
               # Replace Windows newlines with Unix    "REFAREA": "MDG_LDC",
               # Replace Windows newlines with Unix    "LOCATION": "T",
               # Replace Windows newlines with Unix    "AGEGROUP": "000_099_Y",
               # Replace Windows newlines with Unix    "SEX": "F",
               # Replace Windows newlines with Unix    "TIMEPERIOD": "2013",
               # Replace Windows newlines with Unix    "UNIT": "PERCENT",
               # Replace Windows newlines with Unix    "UNITMULT": "0",
               # Replace Windows newlines with Unix    "OBSVALUE": "66",
               # Replace Windows newlines with Unix    "NATURE": "NA",
               # Replace Windows newlines with Unix    "SOURCETYPE": "NA",
               # Replace Windows newlines with Unix    "SOURCEDETAIL": null,
               # Replace Windows newlines with Unix    "TIMEDETAIL": "2013",
               # Replace Windows newlines with Unix    "FOOTNOTES": null
               # Replace Windows newlines with Unix  },
               # Replace Windows newlines with Unix  {
               # Replace Windows newlines with Unix    "SERIES": "SE_SEC_TRTCHRTCH",
               # Replace Windows newlines with Unix    "FREQ": "A",
               # Replace Windows newlines with Unix    "REFAREA": "MDG_LLDC",
               # Replace Windows newlines with Unix    "LOCATION": "T",
               # Replace Windows newlines with Unix    "AGEGROUP": "000_099_Y",
               # Replace Windows newlines with Unix    "SEX": "F",
               # Replace Windows newlines with Unix    "TIMEPERIOD": "2005",
               # Replace Windows newlines with Unix    "UNIT": "PERCENT",
               # Replace Windows newlines with Unix    "UNITMULT": "0",
               # Replace Windows newlines with Unix    "OBSVALUE": "92",
               # Replace Windows newlines with Unix    "NATURE": "NA",
               # Replace Windows newlines with Unix    "SOURCETYPE": "NA",
               # Replace Windows newlines with Unix    "SOURCEDETAIL": null,
               # Replace Windows newlines with Unix    "TIMEDETAIL": "2005",
               # Replace Windows newlines with Unix    "FOOTNOTES": null
               # Replace Windows newlines with Unix  },
               # Replace Windows newlines with Unix  {
               # Replace Windows newlines with Unix    "SERIES": "SE_SEC_TRTCHRTCH",
               # Replace Windows newlines with Unix    "FREQ": "A",
               # Replace Windows newlines with Unix    "REFAREA": "MDG_LLDC",
               # Replace Windows newlines with Unix    "LOCATION": "T",
               # Replace Windows newlines with Unix    "AGEGROUP": "000_099_Y",
               # Replace Windows newlines with Unix    "SEX": "F",
               # Replace Windows newlines with Unix    "TIMEPERIOD": "2010",
               # Replace Windows newlines with Unix    "UNIT": "PERCENT",
               # Replace Windows newlines with Unix    "UNITMULT": "0",
               # Replace Windows newlines with Unix    "OBSVALUE": "89",
               # Replace Windows newlines with Unix    "NATURE": "NA",
               # Replace Windows newlines with Unix    "SOURCETYPE": "NA",
               # Replace Windows newlines with Unix    "SOURCEDETAIL": null,
               # Replace Windows newlines with Unix    "TIMEDETAIL": "2010",
               # Replace Windows newlines with Unix    "FOOTNOTES": null
               # Replace Windows newlines with Unix  },
               # Replace Windows newlines with Unix  {
               # Replace Windows newlines with Unix    "SERIES": "SE_SEC_TRTCHRTCH",
               # Replace Windows newlines with Unix    "FREQ": "A",
               # Replace Windows newlines with Unix    "REFAREA": "MDG_LLDC",
               # Replace Windows newlines with Unix    "LOCATION": "T",
               # Replace Windows newlines with Unix    "AGEGROUP": "000_099_Y",
               # Replace Windows newlines with Unix    "SEX": "F",
               # Replace Windows newlines with Unix    "TIMEPERIOD": "2012",
               # Replace Windows newlines with Unix    "UNIT": "PERCENT",
               # Replace Windows newlines with Unix    "UNITMULT": "0",
               # Replace Windows newlines with Unix    "OBSVALUE": "86",
               # Replace Windows newlines with Unix    "NATURE": "NA",
               # Replace Windows newlines with Unix    "SOURCETYPE": "NA",
               # Replace Windows newlines with Unix    "SOURCEDETAIL": null,
               # Replace Windows newlines with Unix    "TIMEDETAIL": "2012",
               # Replace Windows newlines with Unix    "FOOTNOTES": null
               # Replace Windows newlines with Unix  },
               # Replace Windows newlines with Unix  {
               # Replace Windows newlines with Unix    "SERIES": "SE_SEC_TRTCHRTCH",
               # Replace Windows newlines with Unix    "FREQ": "A",
               # Replace Windows newlines with Unix    "REFAREA": "MDG_OCE",
               # Replace Windows newlines with Unix    "LOCATION": "T",
               # Replace Windows newlines with Unix    "AGEGROUP": "000_099_Y",
               # Replace Windows newlines with Unix    "SEX": "F",
               # Replace Windows newlines with Unix    "TIMEPERIOD": "2000",
               # Replace Windows newlines with Unix    "UNIT": "PERCENT",
               # Replace Windows newlines with Unix    "UNITMULT": "0",
               # Replace Windows newlines with Unix    "OBSVALUE": "89",
               # Replace Windows newlines with Unix    "NATURE": "NA",
               # Replace Windows newlines with Unix    "SOURCETYPE": "NA",
               # Replace Windows newlines with Unix    "SOURCEDETAIL": null,
               # Replace Windows newlines with Unix    "TIMEDETAIL": "2000",
               # Replace Windows newlines with Unix    "FOOTNOTES": null
               # Replace Windows newlines with Unix  },
               # Replace Windows newlines with Unix  {
               # Replace Windows newlines with Unix    "SERIES": "SE_SEC_TRTCHRTCH",
               # Replace Windows newlines with Unix    "FREQ": "A",
               # Replace Windows newlines with Unix    "REFAREA": "MDG_OCE",
               # Replace Windows newlines with Unix    "LOCATION": "T",
               # Replace Windows newlines with Unix    "AGEGROUP": "000_099_Y",
               # Replace Windows newlines with Unix    "SEX": "F",
               # Replace Windows newlines with Unix    "TIMEPERIOD": "2005",
               # Replace Windows newlines with Unix    "UNIT": "PERCENT",
               # Replace Windows newlines with Unix    "UNITMULT": "0",
               # Replace Windows newlines with Unix    "OBSVALUE": "92",
               # Replace Windows newlines with Unix    "NATURE": "NA",
               # Replace Windows newlines with Unix    "SOURCETYPE": "NA",
               # Replace Windows newlines with Unix    "SOURCEDETAIL": null,
               # Replace Windows newlines with Unix    "TIMEDETAIL": "2005",
               # Replace Windows newlines with Unix    "FOOTNOTES": null
               # Replace Windows newlines with Unix  },
               # Replace Windows newlines with Unix  {
               # Replace Windows newlines with Unix    "SERIES": "SE_SEC_TRTCHRTCH",
               # Replace Windows newlines with Unix    "FREQ": "A",
               # Replace Windows newlines with Unix    "REFAREA": "MDG_OCE",
               # Replace Windows newlines with Unix    "LOCATION": "T",
               # Replace Windows newlines with Unix    "AGEGROUP": "000_099_Y",
               # Replace Windows newlines with Unix    "SEX": "F",
               # Replace Windows newlines with Unix    "TIMEPERIOD": "2010",
               # Replace Windows newlines with Unix    "UNIT": "PERCENT",
               # Replace Windows newlines with Unix    "UNITMULT": "0",
               # Replace Windows newlines with Unix    "OBSVALUE": "88",
               # Replace Windows newlines with Unix    "NATURE": "NA",
               # Replace Windows newlines with Unix    "SOURCETYPE": "NA",
               # Replace Windows newlines with Unix    "SOURCEDETAIL": null,
               # Replace Windows newlines with Unix    "TIMEDETAIL": "2010",
               # Replace Windows newlines with Unix    "FOOTNOTES": null
               # Replace Windows newlines with Unix  },
               # Replace Windows newlines with Unix  {
               # Replace Windows newlines with Unix    "SERIES": "SE_SEC_TRTCHRTCH",
               # Replace Windows newlines with Unix    "FREQ": "A",
               # Replace Windows newlines with Unix    "REFAREA": "MDG_OCE",
               # Replace Windows newlines with Unix    "LOCATION": "T",
               # Replace Windows newlines with Unix    "AGEGROUP": "000_099_Y",
               # Replace Windows newlines with Unix    "SEX": "F",
               # Replace Windows newlines with Unix    "TIMEPERIOD": "2013",
               # Replace Windows newlines with Unix    "UNIT": "PERCENT",
               # Replace Windows newlines with Unix    "UNITMULT": "0",
               # Replace Windows newlines with Unix    "OBSVALUE": "91",
               # Replace Windows newlines with Unix    "NATURE": "NA",
               # Replace Windows newlines with Unix    "SOURCETYPE": "NA",
               # Replace Windows newlines with Unix    "SOURCEDETAIL": null,
               # Replace Windows newlines with Unix    "TIMEDETAIL": "2013",
               # Replace Windows newlines with Unix    "FOOTNOTES": null
               # Replace Windows newlines with Unix  },
               # Replace Windows newlines with Unix  {
               # Replace Windows newlines with Unix    "SERIES": "SE_SEC_TRTCHRTCH",
               # Replace Windows newlines with Unix    "FREQ": "A",
               # Replace Windows newlines with Unix    "REFAREA": "MDG_SIDS",
               # Replace Windows newlines with Unix    "LOCATION": "T",
               # Replace Windows newlines with Unix    "AGEGROUP": "000_099_Y",
               # Replace Windows newlines with Unix    "SEX": "F",
               # Replace Windows newlines with Unix    "TIMEPERIOD": "2000",
               # Replace Windows newlines with Unix    "UNIT": "PERCENT",
               # Replace Windows newlines with Unix    "UNITMULT": "0",
               # Replace Windows newlines with Unix    "OBSVALUE": "80",
               # Replace Windows newlines with Unix    "NATURE": "NA",
               # Replace Windows newlines with Unix    "SOURCETYPE": "NA",
               # Replace Windows newlines with Unix    "SOURCEDETAIL": null,
               # Replace Windows newlines with Unix    "TIMEDETAIL": "2000",
               # Replace Windows newlines with Unix    "FOOTNOTES": null
               # Replace Windows newlines with Unix  },
               # Replace Windows newlines with Unix  {
               # Replace Windows newlines with Unix    "SERIES": "SE_SEC_TRTCHRTCH",
               # Replace Windows newlines with Unix    "FREQ": "A",
               # Replace Windows newlines with Unix    "REFAREA": "MDG_SIDS",
               # Replace Windows newlines with Unix    "LOCATION": "T",
               # Replace Windows newlines with Unix    "AGEGROUP": "000_099_Y",
               # Replace Windows newlines with Unix    "SEX": "F",
               # Replace Windows newlines with Unix    "TIMEPERIOD": "2005",
               # Replace Windows newlines with Unix    "UNIT": "PERCENT",
               # Replace Windows newlines with Unix    "UNITMULT": "0",
               # Replace Windows newlines with Unix    "OBSVALUE": "83",
               # Replace Windows newlines with Unix    "NATURE": "NA",
               # Replace Windows newlines with Unix    "SOURCETYPE": "NA",
               # Replace Windows newlines with Unix    "SOURCEDETAIL": null,
               # Replace Windows newlines with Unix    "TIMEDETAIL": "2005",
               # Replace Windows newlines with Unix    "FOOTNOTES": null
               # Replace Windows newlines with Unix  },
               # Replace Windows newlines with Unix  {
               # Replace Windows newlines with Unix    "SERIES": "SE_SEC_TRTCHRTCH",
               # Replace Windows newlines with Unix    "FREQ": "A",
               # Replace Windows newlines with Unix    "REFAREA": "MDG_SIDS",
               # Replace Windows newlines with Unix    "LOCATION": "T",
               # Replace Windows newlines with Unix    "AGEGROUP": "000_099_Y",
               # Replace Windows newlines with Unix    "SEX": "F",
               # Replace Windows newlines with Unix    "TIMEPERIOD": "2010",
               # Replace Windows newlines with Unix    "UNIT": "PERCENT",
               # Replace Windows newlines with Unix    "UNITMULT": "0",
               # Replace Windows newlines with Unix    "OBSVALUE": "80",
               # Replace Windows newlines with Unix    "NATURE": "NA",
               # Replace Windows newlines with Unix    "SOURCETYPE": "NA",
               # Replace Windows newlines with Unix    "SOURCEDETAIL": null,
               # Replace Windows newlines with Unix    "TIMEDETAIL": "2010",
               # Replace Windows newlines with Unix    "FOOTNOTES": null
               # Replace Windows newlines with Unix  },
               # Replace Windows newlines with Unix  {
               # Replace Windows newlines with Unix    "SERIES": "SE_SEC_TRTCHRTCH",
               # Replace Windows newlines with Unix    "FREQ": "A",
               # Replace Windows newlines with Unix    "REFAREA": "MDG_SIDS",
               # Replace Windows newlines with Unix    "LOCATION": "T",
               # Replace Windows newlines with Unix    "AGEGROUP": "000_099_Y",
               # Replace Windows newlines with Unix    "SEX": "F",
               # Replace Windows newlines with Unix    "TIMEPERIOD": "2013",
               # Replace Windows newlines with Unix    "UNIT": "PERCENT",
               # Replace Windows newlines with Unix    "UNITMULT": "0",
               # Replace Windows newlines with Unix    "OBSVALUE": "79",
               # Replace Windows newlines with Unix    "NATURE": "NA",
               # Replace Windows newlines with Unix    "SOURCETYPE": "NA",
               # Replace Windows newlines with Unix    "SOURCEDETAIL": null,
               # Replace Windows newlines with Unix    "TIMEDETAIL": "2013",
               # Replace Windows newlines with Unix    "FOOTNOTES": null
               # Replace Windows newlines with Unix  },
               # Replace Windows newlines with Unix  {
               # Replace Windows newlines with Unix    "SERIES": "SE_SEC_TRTCHRTCH",
               # Replace Windows newlines with Unix    "FREQ": "A",
               # Replace Windows newlines with Unix    "REFAREA": "MDG_SSA",
               # Replace Windows newlines with Unix    "LOCATION": "T",
               # Replace Windows newlines with Unix    "AGEGROUP": "000_099_Y",
               # Replace Windows newlines with Unix    "SEX": "F",
               # Replace Windows newlines with Unix    "TIMEPERIOD": "2007",
               # Replace Windows newlines with Unix    "UNIT": "PERCENT",
               # Replace Windows newlines with Unix    "UNITMULT": "0",
               # Replace Windows newlines with Unix    "OBSVALUE": "67",
               # Replace Windows newlines with Unix    "NATURE": "NA",
               # Replace Windows newlines with Unix    "SOURCETYPE": "NA",
               # Replace Windows newlines with Unix    "SOURCEDETAIL": null,
               # Replace Windows newlines with Unix    "TIMEDETAIL": "2007",
               # Replace Windows newlines with Unix    "FOOTNOTES": null
               # Replace Windows newlines with Unix  },
               # Replace Windows newlines with Unix  {
               # Replace Windows newlines with Unix    "SERIES": "SE_SEC_TRTCHRTCH",
               # Replace Windows newlines with Unix    "FREQ": "A",
               # Replace Windows newlines with Unix    "REFAREA": "MDG_SSA",
               # Replace Windows newlines with Unix    "LOCATION": "T",
               # Replace Windows newlines with Unix    "AGEGROUP": "000_099_Y",
               # Replace Windows newlines with Unix    "SEX": "F",
               # Replace Windows newlines with Unix    "TIMEPERIOD": "2010",
               # Replace Windows newlines with Unix    "UNIT": "PERCENT",
               # Replace Windows newlines with Unix    "UNITMULT": "0",
               # Replace Windows newlines with Unix    "OBSVALUE": "66",
               # Replace Windows newlines with Unix    "NATURE": "NA",
               # Replace Windows newlines with Unix    "SOURCETYPE": "NA",
               # Replace Windows newlines with Unix    "SOURCEDETAIL": null,
               # Replace Windows newlines with Unix    "TIMEDETAIL": "2010",
               # Replace Windows newlines with Unix    "FOOTNOTES": null
               # Replace Windows newlines with Unix  },
               # Replace Windows newlines with Unix  {
               # Replace Windows newlines with Unix    "SERIES": "SE_SEC_TRTCHRTCH",
               # Replace Windows newlines with Unix    "FREQ": "A",
               # Replace Windows newlines with Unix    "REFAREA": "MDG_SSA",
               # Replace Windows newlines with Unix    "LOCATION": "T",
               # Replace Windows newlines with Unix    "AGEGROUP": "000_099_Y",
               # Replace Windows newlines with Unix    "SEX": "F",
               # Replace Windows newlines with Unix    "TIMEPERIOD": "2013",
               # Replace Windows newlines with Unix    "UNIT": "PERCENT",
               # Replace Windows newlines with Unix    "UNITMULT": "0",
               # Replace Windows newlines with Unix    "OBSVALUE": "60",
               # Replace Windows newlines with Unix    "NATURE": "NA",
               # Replace Windows newlines with Unix    "SOURCETYPE": "NA",
               # Replace Windows newlines with Unix    "SOURCEDETAIL": null,
               # Replace Windows newlines with Unix    "TIMEDETAIL": "2013",
               # Replace Windows newlines with Unix    "FOOTNOTES": null
               # Replace Windows newlines with Unix  },
               # Replace Windows newlines with Unix  {
               # Replace Windows newlines with Unix    "SERIES": "SE_SEC_TRTCHRTCH",
               # Replace Windows newlines with Unix    "FREQ": "A",
               # Replace Windows newlines with Unix    "REFAREA": "CAU_CEN_ASIA",
               # Replace Windows newlines with Unix    "LOCATION": "T",
               # Replace Windows newlines with Unix    "AGEGROUP": "000_099_Y",
               # Replace Windows newlines with Unix    "SEX": "M",
               # Replace Windows newlines with Unix    "TIMEPERIOD": "2005",
               # Replace Windows newlines with Unix    "UNIT": "PERCENT",
               # Replace Windows newlines with Unix    "UNITMULT": "0",
               # Replace Windows newlines with Unix    "OBSVALUE": "93",
               # Replace Windows newlines with Unix    "NATURE": "NA",
               # Replace Windows newlines with Unix    "SOURCETYPE": "NA",
               # Replace Windows newlines with Unix    "SOURCEDETAIL": null,
               # Replace Windows newlines with Unix    "TIMEDETAIL": "2005",
               # Replace Windows newlines with Unix    "FOOTNOTES": null
               # Replace Windows newlines with Unix  },
               # Replace Windows newlines with Unix  {
               # Replace Windows newlines with Unix    "SERIES": "SE_SEC_TRTCHRTCH",
               # Replace Windows newlines with Unix    "FREQ": "A",
               # Replace Windows newlines with Unix    "REFAREA": "CAU_CEN_ASIA",
               # Replace Windows newlines with Unix    "LOCATION": "T",
               # Replace Windows newlines with Unix    "AGEGROUP": "000_099_Y",
               # Replace Windows newlines with Unix    "SEX": "M",
               # Replace Windows newlines with Unix    "TIMEPERIOD": "2010",
               # Replace Windows newlines with Unix    "UNIT": "PERCENT",
               # Replace Windows newlines with Unix    "UNITMULT": "0",
               # Replace Windows newlines with Unix    "OBSVALUE": "97",
               # Replace Windows newlines with Unix    "NATURE": "NA",
               # Replace Windows newlines with Unix    "SOURCETYPE": "NA",
               # Replace Windows newlines with Unix    "SOURCEDETAIL": null,
               # Replace Windows newlines with Unix    "TIMEDETAIL": "2010",
               # Replace Windows newlines with Unix    "FOOTNOTES": null
               # Replace Windows newlines with Unix  },
               # Replace Windows newlines with Unix  {
               # Replace Windows newlines with Unix    "SERIES": "SE_SEC_TRTCHRTCH",
               # Replace Windows newlines with Unix    "FREQ": "A",
               # Replace Windows newlines with Unix    "REFAREA": "CAU_CEN_ASIA",
               # Replace Windows newlines with Unix    "LOCATION": "T",
               # Replace Windows newlines with Unix    "AGEGROUP": "000_099_Y",
               # Replace Windows newlines with Unix    "SEX": "M",
               # Replace Windows newlines with Unix    "TIMEPERIOD": "2012",
               # Replace Windows newlines with Unix    "UNIT": "PERCENT",
               # Replace Windows newlines with Unix    "UNITMULT": "0",
               # Replace Windows newlines with Unix    "OBSVALUE": "95",
               # Replace Windows newlines with Unix    "NATURE": "NA",
               # Replace Windows newlines with Unix    "SOURCETYPE": "NA",
               # Replace Windows newlines with Unix    "SOURCEDETAIL": null,
               # Replace Windows newlines with Unix    "TIMEDETAIL": "2012",
               # Replace Windows newlines with Unix    "FOOTNOTES": null
               # Replace Windows newlines with Unix  },
               # Replace Windows newlines with Unix  {
               # Replace Windows newlines with Unix    "SERIES": "SE_SEC_TRTCHRTCH",
               # Replace Windows newlines with Unix    "FREQ": "A",
               # Replace Windows newlines with Unix    "REFAREA": "MDG_LDC",
               # Replace Windows newlines with Unix    "LOCATION": "T",
               # Replace Windows newlines with Unix    "AGEGROUP": "000_099_Y",
               # Replace Windows newlines with Unix    "SEX": "M",
               # Replace Windows newlines with Unix    "TIMEPERIOD": "2000",
               # Replace Windows newlines with Unix    "UNIT": "PERCENT",
               # Replace Windows newlines with Unix    "UNITMULT": "0",
               # Replace Windows newlines with Unix    "OBSVALUE": "62",
               # Replace Windows newlines with Unix    "NATURE": "NA",
               # Replace Windows newlines with Unix    "SOURCETYPE": "NA",
               # Replace Windows newlines with Unix    "SOURCEDETAIL": null,
               # Replace Windows newlines with Unix    "TIMEDETAIL": "2000",
               # Replace Windows newlines with Unix    "FOOTNOTES": null
               # Replace Windows newlines with Unix  },
               # Replace Windows newlines with Unix  {
               # Replace Windows newlines with Unix    "SERIES": "SE_SEC_TRTCHRTCH",
               # Replace Windows newlines with Unix    "FREQ": "A",
               # Replace Windows newlines with Unix    "REFAREA": "MDG_LDC",
               # Replace Windows newlines with Unix    "LOCATION": "T",
               # Replace Windows newlines with Unix    "AGEGROUP": "000_099_Y",
               # Replace Windows newlines with Unix    "SEX": "M",
               # Replace Windows newlines with Unix    "TIMEPERIOD": "2005",
               # Replace Windows newlines with Unix    "UNIT": "PERCENT",
               # Replace Windows newlines with Unix    "UNITMULT": "0",
               # Replace Windows newlines with Unix    "OBSVALUE": "56",
               # Replace Windows newlines with Unix    "NATURE": "NA",
               # Replace Windows newlines with Unix    "SOURCETYPE": "NA",
               # Replace Windows newlines with Unix    "SOURCEDETAIL": null,
               # Replace Windows newlines with Unix    "TIMEDETAIL": "2005",
               # Replace Windows newlines with Unix    "FOOTNOTES": null
               # Replace Windows newlines with Unix  },
               # Replace Windows newlines with Unix  {
               # Replace Windows newlines with Unix    "SERIES": "SE_SEC_TRTCHRTCH",
               # Replace Windows newlines with Unix    "FREQ": "A",
               # Replace Windows newlines with Unix    "REFAREA": "MDG_LDC",
               # Replace Windows newlines with Unix    "LOCATION": "T",
               # Replace Windows newlines with Unix    "AGEGROUP": "000_099_Y",
               # Replace Windows newlines with Unix    "SEX": "M",
               # Replace Windows newlines with Unix    "TIMEPERIOD": "2010",
               # Replace Windows newlines with Unix    "UNIT": "PERCENT",
               # Replace Windows newlines with Unix    "UNITMULT": "0",
               # Replace Windows newlines with Unix    "OBSVALUE": "55",
               # Replace Windows newlines with Unix    "NATURE": "NA",
               # Replace Windows newlines with Unix    "SOURCETYPE": "NA",
               # Replace Windows newlines with Unix    "SOURCEDETAIL": null,
               # Replace Windows newlines with Unix    "TIMEDETAIL": "2010",
               # Replace Windows newlines with Unix    "FOOTNOTES": null
               # Replace Windows newlines with Unix  },
               # Replace Windows newlines with Unix  {
               # Replace Windows newlines with Unix    "SERIES": "SE_SEC_TRTCHRTCH",
               # Replace Windows newlines with Unix    "FREQ": "A",
               # Replace Windows newlines with Unix    "REFAREA": "MDG_LDC",
               # Replace Windows newlines with Unix    "LOCATION": "T",
               # Replace Windows newlines with Unix    "AGEGROUP": "000_099_Y",
               # Replace Windows newlines with Unix    "SEX": "M",
               # Replace Windows newlines with Unix    "TIMEPERIOD": "2013",
               # Replace Windows newlines with Unix    "UNIT": "PERCENT",
               # Replace Windows newlines with Unix    "UNITMULT": "0",
               # Replace Windows newlines with Unix    "OBSVALUE": "53",
               # Replace Windows newlines with Unix    "NATURE": "NA",
               # Replace Windows newlines with Unix    "SOURCETYPE": "NA",
               # Replace Windows newlines with Unix    "SOURCEDETAIL": null,
               # Replace Windows newlines with Unix    "TIMEDETAIL": "2013",
               # Replace Windows newlines with Unix    "FOOTNOTES": null
               # Replace Windows newlines with Unix  },
               # Replace Windows newlines with Unix  {
               # Replace Windows newlines with Unix    "SERIES": "SE_SEC_TRTCHRTCH",
               # Replace Windows newlines with Unix    "FREQ": "A",
               # Replace Windows newlines with Unix    "REFAREA": "MDG_LLDC",
               # Replace Windows newlines with Unix    "LOCATION": "T",
               # Replace Windows newlines with Unix    "AGEGROUP": "000_099_Y",
               # Replace Windows newlines with Unix    "SEX": "M",
               # Replace Windows newlines with Unix    "TIMEPERIOD": "2005",
               # Replace Windows newlines with Unix    "UNIT": "PERCENT",
               # Replace Windows newlines with Unix    "UNITMULT": "0",
               # Replace Windows newlines with Unix    "OBSVALUE": "83",
               # Replace Windows newlines with Unix    "NATURE": "NA",
               # Replace Windows newlines with Unix    "SOURCETYPE": "NA",
               # Replace Windows newlines with Unix    "SOURCEDETAIL": null,
               # Replace Windows newlines with Unix    "TIMEDETAIL": "2005",
               # Replace Windows newlines with Unix    "FOOTNOTES": null
               # Replace Windows newlines with Unix  },
               # Replace Windows newlines with Unix  {
               # Replace Windows newlines with Unix    "SERIES": "SE_SEC_TRTCHRTCH",
               # Replace Windows newlines with Unix    "FREQ": "A",
               # Replace Windows newlines with Unix    "REFAREA": "MDG_LLDC",
               # Replace Windows newlines with Unix    "LOCATION": "T",
               # Replace Windows newlines with Unix    "AGEGROUP": "000_099_Y",
               # Replace Windows newlines with Unix    "SEX": "M",
               # Replace Windows newlines with Unix    "TIMEPERIOD": "2010",
               # Replace Windows newlines with Unix    "UNIT": "PERCENT",
               # Replace Windows newlines with Unix    "UNITMULT": "0",
               # Replace Windows newlines with Unix    "OBSVALUE": "76",
               # Replace Windows newlines with Unix    "NATURE": "NA",
               # Replace Windows newlines with Unix    "SOURCETYPE": "NA",
               # Replace Windows newlines with Unix    "SOURCEDETAIL": null,
               # Replace Windows newlines with Unix    "TIMEDETAIL": "2010",
               # Replace Windows newlines with Unix    "FOOTNOTES": null
               # Replace Windows newlines with Unix  },
               # Replace Windows newlines with Unix  {
               # Replace Windows newlines with Unix    "SERIES": "SE_SEC_TRTCHRTCH",
               # Replace Windows newlines with Unix    "FREQ": "A",
               # Replace Windows newlines with Unix    "REFAREA": "MDG_LLDC",
               # Replace Windows newlines with Unix    "LOCATION": "T",
               # Replace Windows newlines with Unix    "AGEGROUP": "000_099_Y",
               # Replace Windows newlines with Unix    "SEX": "M",
               # Replace Windows newlines with Unix    "TIMEPERIOD": "2012",
               # Replace Windows newlines with Unix    "UNIT": "PERCENT",
               # Replace Windows newlines with Unix    "UNITMULT": "0",
               # Replace Windows newlines with Unix    "OBSVALUE": "76",
               # Replace Windows newlines with Unix    "NATURE": "NA",
               # Replace Windows newlines with Unix    "SOURCETYPE": "NA",
               # Replace Windows newlines with Unix    "SOURCEDETAIL": null,
               # Replace Windows newlines with Unix    "TIMEDETAIL": "2012",
               # Replace Windows newlines with Unix    "FOOTNOTES": null
               # Replace Windows newlines with Unix  },
               # Replace Windows newlines with Unix  {
               # Replace Windows newlines with Unix    "SERIES": "SE_SEC_TRTCHRTCH",
               # Replace Windows newlines with Unix    "FREQ": "A",
               # Replace Windows newlines with Unix    "REFAREA": "MDG_OCE",
               # Replace Windows newlines with Unix    "LOCATION": "T",
               # Replace Windows newlines with Unix    "AGEGROUP": "000_099_Y",
               # Replace Windows newlines with Unix    "SEX": "M",
               # Replace Windows newlines with Unix    "TIMEPERIOD": "2000",
               # Replace Windows newlines with Unix    "UNIT": "PERCENT",
               # Replace Windows newlines with Unix    "UNITMULT": "0",
               # Replace Windows newlines with Unix    "OBSVALUE": "91",
               # Replace Windows newlines with Unix    "NATURE": "NA",
               # Replace Windows newlines with Unix    "SOURCETYPE": "NA",
               # Replace Windows newlines with Unix    "SOURCEDETAIL": null,
               # Replace Windows newlines with Unix    "TIMEDETAIL": "2000",
               # Replace Windows newlines with Unix    "FOOTNOTES": null
               # Replace Windows newlines with Unix  },
               # Replace Windows newlines with Unix  {
               # Replace Windows newlines with Unix    "SERIES": "SE_SEC_TRTCHRTCH",
               # Replace Windows newlines with Unix    "FREQ": "A",
               # Replace Windows newlines with Unix    "REFAREA": "MDG_OCE",
               # Replace Windows newlines with Unix    "LOCATION": "T",
               # Replace Windows newlines with Unix    "AGEGROUP": "000_099_Y",
               # Replace Windows newlines with Unix    "SEX": "M",
               # Replace Windows newlines with Unix    "TIMEPERIOD": "2005",
               # Replace Windows newlines with Unix    "UNIT": "PERCENT",
               # Replace Windows newlines with Unix    "UNITMULT": "0",
               # Replace Windows newlines with Unix    "OBSVALUE": "93",
               # Replace Windows newlines with Unix    "NATURE": "NA",
               # Replace Windows newlines with Unix    "SOURCETYPE": "NA",
               # Replace Windows newlines with Unix    "SOURCEDETAIL": null,
               # Replace Windows newlines with Unix    "TIMEDETAIL": "2005",
               # Replace Windows newlines with Unix    "FOOTNOTES": null
               # Replace Windows newlines with Unix  },
               # Replace Windows newlines with Unix  {
               # Replace Windows newlines with Unix    "SERIES": "SE_SEC_TRTCHRTCH",
               # Replace Windows newlines with Unix    "FREQ": "A",
               # Replace Windows newlines with Unix    "REFAREA": "MDG_OCE",
               # Replace Windows newlines with Unix    "LOCATION": "T",
               # Replace Windows newlines with Unix    "AGEGROUP": "000_099_Y",
               # Replace Windows newlines with Unix    "SEX": "M",
               # Replace Windows newlines with Unix    "TIMEPERIOD": "2010",
               # Replace Windows newlines with Unix    "UNIT": "PERCENT",
               # Replace Windows newlines with Unix    "UNITMULT": "0",
               # Replace Windows newlines with Unix    "OBSVALUE": "93",
               # Replace Windows newlines with Unix    "NATURE": "NA",
               # Replace Windows newlines with Unix    "SOURCETYPE": "NA",
               # Replace Windows newlines with Unix    "SOURCEDETAIL": null,
               # Replace Windows newlines with Unix    "TIMEDETAIL": "2010",
               # Replace Windows newlines with Unix    "FOOTNOTES": null
               # Replace Windows newlines with Unix  },
               # Replace Windows newlines with Unix  {
               # Replace Windows newlines with Unix    "SERIES": "SE_SEC_TRTCHRTCH",
               # Replace Windows newlines with Unix    "FREQ": "A",
               # Replace Windows newlines with Unix    "REFAREA": "MDG_OCE",
               # Replace Windows newlines with Unix    "LOCATION": "T",
               # Replace Windows newlines with Unix    "AGEGROUP": "000_099_Y",
               # Replace Windows newlines with Unix    "SEX": "M",
               # Replace Windows newlines with Unix    "TIMEPERIOD": "2013",
               # Replace Windows newlines with Unix    "UNIT": "PERCENT",
               # Replace Windows newlines with Unix    "UNITMULT": "0",
               # Replace Windows newlines with Unix    "OBSVALUE": "91",
               # Replace Windows newlines with Unix    "NATURE": "NA",
               # Replace Windows newlines with Unix    "SOURCETYPE": "NA",
               # Replace Windows newlines with Unix    "SOURCEDETAIL": null,
               # Replace Windows newlines with Unix    "TIMEDETAIL": "2013",
               # Replace Windows newlines with Unix    "FOOTNOTES": null
               # Replace Windows newlines with Unix  },
               # Replace Windows newlines with Unix  {
               # Replace Windows newlines with Unix    "SERIES": "SE_SEC_TRTCHRTCH",
               # Replace Windows newlines with Unix    "FREQ": "A",
               # Replace Windows newlines with Unix    "REFAREA": "MDG_SIDS",
               # Replace Windows newlines with Unix    "LOCATION": "T",
               # Replace Windows newlines with Unix    "AGEGROUP": "000_099_Y",
               # Replace Windows newlines with Unix    "SEX": "M",
               # Replace Windows newlines with Unix    "TIMEPERIOD": "2000",
               # Replace Windows newlines with Unix    "UNIT": "PERCENT",
               # Replace Windows newlines with Unix    "UNITMULT": "0",
               # Replace Windows newlines with Unix    "OBSVALUE": "79",
               # Replace Windows newlines with Unix    "NATURE": "NA",
               # Replace Windows newlines with Unix    "SOURCETYPE": "NA",
               # Replace Windows newlines with Unix    "SOURCEDETAIL": null,
               # Replace Windows newlines with Unix    "TIMEDETAIL": "2000",
               # Replace Windows newlines with Unix    "FOOTNOTES": null
               # Replace Windows newlines with Unix  },
               # Replace Windows newlines with Unix  {
               # Replace Windows newlines with Unix    "SERIES": "SE_SEC_TRTCHRTCH",
               # Replace Windows newlines with Unix    "FREQ": "A",
               # Replace Windows newlines with Unix    "REFAREA": "MDG_SIDS",
               # Replace Windows newlines with Unix    "LOCATION": "T",
               # Replace Windows newlines with Unix    "AGEGROUP": "000_099_Y",
               # Replace Windows newlines with Unix    "SEX": "M",
               # Replace Windows newlines with Unix    "TIMEPERIOD": "2005",
               # Replace Windows newlines with Unix    "UNIT": "PERCENT",
               # Replace Windows newlines with Unix    "UNITMULT": "0",
               # Replace Windows newlines with Unix    "OBSVALUE": "82",
               # Replace Windows newlines with Unix    "NATURE": "NA",
               # Replace Windows newlines with Unix    "SOURCETYPE": "NA",
               # Replace Windows newlines with Unix    "SOURCEDETAIL": null,
               # Replace Windows newlines with Unix    "TIMEDETAIL": "2005",
               # Replace Windows newlines with Unix    "FOOTNOTES": null
               # Replace Windows newlines with Unix  },
               # Replace Windows newlines with Unix  {
               # Replace Windows newlines with Unix    "SERIES": "SE_SEC_TRTCHRTCH",
               # Replace Windows newlines with Unix    "FREQ": "A",
               # Replace Windows newlines with Unix    "REFAREA": "MDG_SIDS",
               # Replace Windows newlines with Unix    "LOCATION": "T",
               # Replace Windows newlines with Unix    "AGEGROUP": "000_099_Y",
               # Replace Windows newlines with Unix    "SEX": "M",
               # Replace Windows newlines with Unix    "TIMEPERIOD": "2010",
               # Replace Windows newlines with Unix    "UNIT": "PERCENT",
               # Replace Windows newlines with Unix    "UNITMULT": "0",
               # Replace Windows newlines with Unix    "OBSVALUE": "82",
               # Replace Windows newlines with Unix    "NATURE": "NA",
               # Replace Windows newlines with Unix    "SOURCETYPE": "NA",
               # Replace Windows newlines with Unix    "SOURCEDETAIL": null,
               # Replace Windows newlines with Unix    "TIMEDETAIL": "2010",
               # Replace Windows newlines with Unix    "FOOTNOTES": null
               # Replace Windows newlines with Unix  },
               # Replace Windows newlines with Unix  {
               # Replace Windows newlines with Unix    "SERIES": "SE_SEC_TRTCHRTCH",
               # Replace Windows newlines with Unix    "FREQ": "A",
               # Replace Windows newlines with Unix    "REFAREA": "MDG_SIDS",
               # Replace Windows newlines with Unix    "LOCATION": "T",
               # Replace Windows newlines with Unix    "AGEGROUP": "000_099_Y",
               # Replace Windows newlines with Unix    "SEX": "M",
               # Replace Windows newlines with Unix    "TIMEPERIOD": "2013",
               # Replace Windows newlines with Unix    "UNIT": "PERCENT",
               # Replace Windows newlines with Unix    "UNITMULT": "0",
               # Replace Windows newlines with Unix    "OBSVALUE": "79",
               # Replace Windows newlines with Unix    "NATURE": "NA",
               # Replace Windows newlines with Unix    "SOURCETYPE": "NA",
               # Replace Windows newlines with Unix    "SOURCEDETAIL": null,
               # Replace Windows newlines with Unix    "TIMEDETAIL": "2013",
               # Replace Windows newlines with Unix    "FOOTNOTES": null
               # Replace Windows newlines with Unix  },
               # Replace Windows newlines with Unix  {
               # Replace Windows newlines with Unix    "SERIES": "SE_SEC_TRTCHRTCH",
               # Replace Windows newlines with Unix    "FREQ": "A",
               # Replace Windows newlines with Unix    "REFAREA": "MDG_SSA",
               # Replace Windows newlines with Unix    "LOCATION": "T",
               # Replace Windows newlines with Unix    "AGEGROUP": "000_099_Y",
               # Replace Windows newlines with Unix    "SEX": "M",
               # Replace Windows newlines with Unix    "TIMEPERIOD": "2007",
               # Replace Windows newlines with Unix    "UNIT": "PERCENT",
               # Replace Windows newlines with Unix    "UNITMULT": "0",
               # Replace Windows newlines with Unix    "OBSVALUE": "60",
               # Replace Windows newlines with Unix    "NATURE": "NA",
               # Replace Windows newlines with Unix    "SOURCETYPE": "NA",
               # Replace Windows newlines with Unix    "SOURCEDETAIL": null,
               # Replace Windows newlines with Unix    "TIMEDETAIL": "2007",
               # Replace Windows newlines with Unix    "FOOTNOTES": null
               # Replace Windows newlines with Unix  },
               # Replace Windows newlines with Unix  {
               # Replace Windows newlines with Unix    "SERIES": "SE_SEC_TRTCHRTCH",
               # Replace Windows newlines with Unix    "FREQ": "A",
               # Replace Windows newlines with Unix    "REFAREA": "MDG_SSA",
               # Replace Windows newlines with Unix    "LOCATION": "T",
               # Replace Windows newlines with Unix    "AGEGROUP": "000_099_Y",
               # Replace Windows newlines with Unix    "SEX": "M",
               # Replace Windows newlines with Unix    "TIMEPERIOD": "2010",
               # Replace Windows newlines with Unix    "UNIT": "PERCENT",
               # Replace Windows newlines with Unix    "UNITMULT": "0",
               # Replace Windows newlines with Unix    "OBSVALUE": "58",
               # Replace Windows newlines with Unix    "NATURE": "NA",
               # Replace Windows newlines with Unix    "SOURCETYPE": "NA",
               # Replace Windows newlines with Unix    "SOURCEDETAIL": null,
               # Replace Windows newlines with Unix    "TIMEDETAIL": "2010",
               # Replace Windows newlines with Unix    "FOOTNOTES": null
               # Replace Windows newlines with Unix  },
               # Replace Windows newlines with Unix  {
               # Replace Windows newlines with Unix    "SERIES": "SE_SEC_TRTCHRTCH",
               # Replace Windows newlines with Unix    "FREQ": "A",
               # Replace Windows newlines with Unix    "REFAREA": "MDG_SSA",
               # Replace Windows newlines with Unix    "LOCATION": "T",
               # Replace Windows newlines with Unix    "AGEGROUP": "000_099_Y",
               # Replace Windows newlines with Unix    "SEX": "M",
               # Replace Windows newlines with Unix    "TIMEPERIOD": "2013",
               # Replace Windows newlines with Unix    "UNIT": "PERCENT",
               # Replace Windows newlines with Unix    "UNITMULT": "0",
               # Replace Windows newlines with Unix    "OBSVALUE": "53",
               # Replace Windows newlines with Unix    "NATURE": "NA",
               # Replace Windows newlines with Unix    "SOURCETYPE": "NA",
               # Replace Windows newlines with Unix    "SOURCEDETAIL": null,
               # Replace Windows newlines with Unix    "TIMEDETAIL": "2013",
               # Replace Windows newlines with Unix    "FOOTNOTES": null
               # Replace Windows newlines with Unix  },
               # Replace Windows newlines with Unix  {
               # Replace Windows newlines with Unix    "SERIES": "SE_SEC_TRTCHRTCH",
               # Replace Windows newlines with Unix    "FREQ": "A",
               # Replace Windows newlines with Unix    "REFAREA": "CAU_CEN_ASIA",
               # Replace Windows newlines with Unix    "LOCATION": "T",
               # Replace Windows newlines with Unix    "AGEGROUP": "000_099_Y",
               # Replace Windows newlines with Unix    "SEX": "T",
               # Replace Windows newlines with Unix    "TIMEPERIOD": "2005",
               # Replace Windows newlines with Unix    "UNIT": "PERCENT",
               # Replace Windows newlines with Unix    "UNITMULT": "0",
               # Replace Windows newlines with Unix    "OBSVALUE": "96",
               # Replace Windows newlines with Unix    "NATURE": "NA",
               # Replace Windows newlines with Unix    "SOURCETYPE": "NA",
               # Replace Windows newlines with Unix    "SOURCEDETAIL": null,
               # Replace Windows newlines with Unix    "TIMEDETAIL": "2005",
               # Replace Windows newlines with Unix    "FOOTNOTES": null
               # Replace Windows newlines with Unix  },
               # Replace Windows newlines with Unix  {
               # Replace Windows newlines with Unix    "SERIES": "SE_SEC_TRTCHRTCH",
               # Replace Windows newlines with Unix    "FREQ": "A",
               # Replace Windows newlines with Unix    "REFAREA": "CAU_CEN_ASIA",
               # Replace Windows newlines with Unix    "LOCATION": "T",
               # Replace Windows newlines with Unix    "AGEGROUP": "000_099_Y",
               # Replace Windows newlines with Unix    "SEX": "T",
               # Replace Windows newlines with Unix    "TIMEPERIOD": "2010",
               # Replace Windows newlines with Unix    "UNIT": "PERCENT",
               # Replace Windows newlines with Unix    "UNITMULT": "0",
               # Replace Windows newlines with Unix    "OBSVALUE": "97",
               # Replace Windows newlines with Unix    "NATURE": "NA",
               # Replace Windows newlines with Unix    "SOURCETYPE": "NA",
               # Replace Windows newlines with Unix    "SOURCEDETAIL": null,
               # Replace Windows newlines with Unix    "TIMEDETAIL": "2010",
               # Replace Windows newlines with Unix    "FOOTNOTES": null
               # Replace Windows newlines with Unix  },
               # Replace Windows newlines with Unix  {
               # Replace Windows newlines with Unix    "SERIES": "SE_SEC_TRTCHRTCH",
               # Replace Windows newlines with Unix    "FREQ": "A",
               # Replace Windows newlines with Unix    "REFAREA": "CAU_CEN_ASIA",
               # Replace Windows newlines with Unix    "LOCATION": "T",
               # Replace Windows newlines with Unix    "AGEGROUP": "000_099_Y",
               # Replace Windows newlines with Unix    "SEX": "T",
               # Replace Windows newlines with Unix    "TIMEPERIOD": "2012",
               # Replace Windows newlines with Unix    "UNIT": "PERCENT",
               # Replace Windows newlines with Unix    "UNITMULT": "0",
               # Replace Windows newlines with Unix    "OBSVALUE": "94",
               # Replace Windows newlines with Unix    "NATURE": "NA",
               # Replace Windows newlines with Unix    "SOURCETYPE": "NA",
               # Replace Windows newlines with Unix    "SOURCEDETAIL": null,
               # Replace Windows newlines with Unix    "TIMEDETAIL": "2012",
               # Replace Windows newlines with Unix    "FOOTNOTES": null
               # Replace Windows newlines with Unix  },
               # Replace Windows newlines with Unix  {
               # Replace Windows newlines with Unix    "SERIES": "SE_SEC_TRTCHRTCH",
               # Replace Windows newlines with Unix    "FREQ": "A",
               # Replace Windows newlines with Unix    "REFAREA": "MDG_LAC",
               # Replace Windows newlines with Unix    "LOCATION": "T",
               # Replace Windows newlines with Unix    "AGEGROUP": "000_099_Y",
               # Replace Windows newlines with Unix    "SEX": "T",
               # Replace Windows newlines with Unix    "TIMEPERIOD": "2007",
               # Replace Windows newlines with Unix    "UNIT": "PERCENT",
               # Replace Windows newlines with Unix    "UNITMULT": "0",
               # Replace Windows newlines with Unix    "OBSVALUE": "82",
               # Replace Windows newlines with Unix    "NATURE": "NA",
               # Replace Windows newlines with Unix    "SOURCETYPE": "NA",
               # Replace Windows newlines with Unix    "SOURCEDETAIL": null,
               # Replace Windows newlines with Unix    "TIMEDETAIL": "2007",
               # Replace Windows newlines with Unix    "FOOTNOTES": null
               # Replace Windows newlines with Unix  },
               # Replace Windows newlines with Unix  {
               # Replace Windows newlines with Unix    "SERIES": "SE_SEC_TRTCHRTCH",
               # Replace Windows newlines with Unix    "FREQ": "A",
               # Replace Windows newlines with Unix    "REFAREA": "MDG_LAC",
               # Replace Windows newlines with Unix    "LOCATION": "T",
               # Replace Windows newlines with Unix    "AGEGROUP": "000_099_Y",
               # Replace Windows newlines with Unix    "SEX": "T",
               # Replace Windows newlines with Unix    "TIMEPERIOD": "2010",
               # Replace Windows newlines with Unix    "UNIT": "PERCENT",
               # Replace Windows newlines with Unix    "UNITMULT": "0",
               # Replace Windows newlines with Unix    "OBSVALUE": "83",
               # Replace Windows newlines with Unix    "NATURE": "NA",
               # Replace Windows newlines with Unix    "SOURCETYPE": "NA",
               # Replace Windows newlines with Unix    "SOURCEDETAIL": null,
               # Replace Windows newlines with Unix    "TIMEDETAIL": "2010",
               # Replace Windows newlines with Unix    "FOOTNOTES": null
               # Replace Windows newlines with Unix  },
               # Replace Windows newlines with Unix  {
               # Replace Windows newlines with Unix    "SERIES": "SE_SEC_TRTCHRTCH",
               # Replace Windows newlines with Unix    "FREQ": "A",
               # Replace Windows newlines with Unix    "REFAREA": "MDG_LDC",
               # Replace Windows newlines with Unix    "LOCATION": "T",
               # Replace Windows newlines with Unix    "AGEGROUP": "000_099_Y",
               # Replace Windows newlines with Unix    "SEX": "T",
               # Replace Windows newlines with Unix    "TIMEPERIOD": "2000",
               # Replace Windows newlines with Unix    "UNIT": "PERCENT",
               # Replace Windows newlines with Unix    "UNITMULT": "0",
               # Replace Windows newlines with Unix    "OBSVALUE": "65",
               # Replace Windows newlines with Unix    "NATURE": "NA",
               # Replace Windows newlines with Unix    "SOURCETYPE": "NA",
               # Replace Windows newlines with Unix    "SOURCEDETAIL": null,
               # Replace Windows newlines with Unix    "TIMEDETAIL": "2000",
               # Replace Windows newlines with Unix    "FOOTNOTES": null
               # Replace Windows newlines with Unix  },
               # Replace Windows newlines with Unix  {
               # Replace Windows newlines with Unix    "SERIES": "SE_SEC_TRTCHRTCH",
               # Replace Windows newlines with Unix    "FREQ": "A",
               # Replace Windows newlines with Unix    "REFAREA": "MDG_LDC",
               # Replace Windows newlines with Unix    "LOCATION": "T",
               # Replace Windows newlines with Unix    "AGEGROUP": "000_099_Y",
               # Replace Windows newlines with Unix    "SEX": "T",
               # Replace Windows newlines with Unix    "TIMEPERIOD": "2005",
               # Replace Windows newlines with Unix    "UNIT": "PERCENT",
               # Replace Windows newlines with Unix    "UNITMULT": "0",
               # Replace Windows newlines with Unix    "OBSVALUE": "59",
               # Replace Windows newlines with Unix    "NATURE": "NA",
               # Replace Windows newlines with Unix    "SOURCETYPE": "NA",
               # Replace Windows newlines with Unix    "SOURCEDETAIL": null,
               # Replace Windows newlines with Unix    "TIMEDETAIL": "2005",
               # Replace Windows newlines with Unix    "FOOTNOTES": null
               # Replace Windows newlines with Unix  },
               # Replace Windows newlines with Unix  {
               # Replace Windows newlines with Unix    "SERIES": "SE_SEC_TRTCHRTCH",
               # Replace Windows newlines with Unix    "FREQ": "A",
               # Replace Windows newlines with Unix    "REFAREA": "MDG_LDC",
               # Replace Windows newlines with Unix    "LOCATION": "T",
               # Replace Windows newlines with Unix    "AGEGROUP": "000_099_Y",
               # Replace Windows newlines with Unix    "SEX": "T",
               # Replace Windows newlines with Unix    "TIMEPERIOD": "2010",
               # Replace Windows newlines with Unix    "UNIT": "PERCENT",
               # Replace Windows newlines with Unix    "UNITMULT": "0",
               # Replace Windows newlines with Unix    "OBSVALUE": "58",
               # Replace Windows newlines with Unix    "NATURE": "NA",
               # Replace Windows newlines with Unix    "SOURCETYPE": "NA",
               # Replace Windows newlines with Unix    "SOURCEDETAIL": null,
               # Replace Windows newlines with Unix    "TIMEDETAIL": "2010",
               # Replace Windows newlines with Unix    "FOOTNOTES": null
               # Replace Windows newlines with Unix  },
               # Replace Windows newlines with Unix  {
               # Replace Windows newlines with Unix    "SERIES": "SE_SEC_TRTCHRTCH",
               # Replace Windows newlines with Unix    "FREQ": "A",
               # Replace Windows newlines with Unix    "REFAREA": "MDG_LDC",
               # Replace Windows newlines with Unix    "LOCATION": "T",
               # Replace Windows newlines with Unix    "AGEGROUP": "000_099_Y",
               # Replace Windows newlines with Unix    "SEX": "T",
               # Replace Windows newlines with Unix    "TIMEPERIOD": "2013",
               # Replace Windows newlines with Unix    "UNIT": "PERCENT",
               # Replace Windows newlines with Unix    "UNITMULT": "0",
               # Replace Windows newlines with Unix    "OBSVALUE": "56",
               # Replace Windows newlines with Unix    "NATURE": "NA",
               # Replace Windows newlines with Unix    "SOURCETYPE": "NA",
               # Replace Windows newlines with Unix    "SOURCEDETAIL": null,
               # Replace Windows newlines with Unix    "TIMEDETAIL": "2013",
               # Replace Windows newlines with Unix    "FOOTNOTES": null
               # Replace Windows newlines with Unix  },
               # Replace Windows newlines with Unix  {
               # Replace Windows newlines with Unix    "SERIES": "SE_SEC_TRTCHRTCH",
               # Replace Windows newlines with Unix    "FREQ": "A",
               # Replace Windows newlines with Unix    "REFAREA": "MDG_LLDC",
               # Replace Windows newlines with Unix    "LOCATION": "T",
               # Replace Windows newlines with Unix    "AGEGROUP": "000_099_Y",
               # Replace Windows newlines with Unix    "SEX": "T",
               # Replace Windows newlines with Unix    "TIMEPERIOD": "2005",
               # Replace Windows newlines with Unix    "UNIT": "PERCENT",
               # Replace Windows newlines with Unix    "UNITMULT": "0",
               # Replace Windows newlines with Unix    "OBSVALUE": "88",
               # Replace Windows newlines with Unix    "NATURE": "NA",
               # Replace Windows newlines with Unix    "SOURCETYPE": "NA",
               # Replace Windows newlines with Unix    "SOURCEDETAIL": null,
               # Replace Windows newlines with Unix    "TIMEDETAIL": "2005",
               # Replace Windows newlines with Unix    "FOOTNOTES": null
               # Replace Windows newlines with Unix  },
               # Replace Windows newlines with Unix  {
               # Replace Windows newlines with Unix    "SERIES": "SE_SEC_TRTCHRTCH",
               # Replace Windows newlines with Unix    "FREQ": "A",
               # Replace Windows newlines with Unix    "REFAREA": "MDG_LLDC",
               # Replace Windows newlines with Unix    "LOCATION": "T",
               # Replace Windows newlines with Unix    "AGEGROUP": "000_099_Y",
               # Replace Windows newlines with Unix    "SEX": "T",
               # Replace Windows newlines with Unix    "TIMEPERIOD": "2010",
               # Replace Windows newlines with Unix    "UNIT": "PERCENT",
               # Replace Windows newlines with Unix    "UNITMULT": "0",
               # Replace Windows newlines with Unix    "OBSVALUE": "83",
               # Replace Windows newlines with Unix    "NATURE": "NA",
               # Replace Windows newlines with Unix    "SOURCETYPE": "NA",
               # Replace Windows newlines with Unix    "SOURCEDETAIL": null,
               # Replace Windows newlines with Unix    "TIMEDETAIL": "2010",
               # Replace Windows newlines with Unix    "FOOTNOTES": null
               # Replace Windows newlines with Unix  },
               # Replace Windows newlines with Unix  {
               # Replace Windows newlines with Unix    "SERIES": "SE_SEC_TRTCHRTCH",
               # Replace Windows newlines with Unix    "FREQ": "A",
               # Replace Windows newlines with Unix    "REFAREA": "MDG_LLDC",
               # Replace Windows newlines with Unix    "LOCATION": "T",
               # Replace Windows newlines with Unix    "AGEGROUP": "000_099_Y",
               # Replace Windows newlines with Unix    "SEX": "T",
               # Replace Windows newlines with Unix    "TIMEPERIOD": "2012",
               # Replace Windows newlines with Unix    "UNIT": "PERCENT",
               # Replace Windows newlines with Unix    "UNITMULT": "0",
               # Replace Windows newlines with Unix    "OBSVALUE": "81",
               # Replace Windows newlines with Unix    "NATURE": "NA",
               # Replace Windows newlines with Unix    "SOURCETYPE": "NA",
               # Replace Windows newlines with Unix    "SOURCEDETAIL": null,
               # Replace Windows newlines with Unix    "TIMEDETAIL": "2012",
               # Replace Windows newlines with Unix    "FOOTNOTES": null
               # Replace Windows newlines with Unix  },
               # Replace Windows newlines with Unix  {
               # Replace Windows newlines with Unix    "SERIES": "SE_SEC_TRTCHRTCH",
               # Replace Windows newlines with Unix    "FREQ": "A",
               # Replace Windows newlines with Unix    "REFAREA": "MDG_OCE",
               # Replace Windows newlines with Unix    "LOCATION": "T",
               # Replace Windows newlines with Unix    "AGEGROUP": "000_099_Y",
               # Replace Windows newlines with Unix    "SEX": "T",
               # Replace Windows newlines with Unix    "TIMEPERIOD": "2000",
               # Replace Windows newlines with Unix    "UNIT": "PERCENT",
               # Replace Windows newlines with Unix    "UNITMULT": "0",
               # Replace Windows newlines with Unix    "OBSVALUE": "90",
               # Replace Windows newlines with Unix    "NATURE": "NA",
               # Replace Windows newlines with Unix    "SOURCETYPE": "NA",
               # Replace Windows newlines with Unix    "SOURCEDETAIL": null,
               # Replace Windows newlines with Unix    "TIMEDETAIL": "2000",
               # Replace Windows newlines with Unix    "FOOTNOTES": null
               # Replace Windows newlines with Unix  },
               # Replace Windows newlines with Unix  {
               # Replace Windows newlines with Unix    "SERIES": "SE_SEC_TRTCHRTCH",
               # Replace Windows newlines with Unix    "FREQ": "A",
               # Replace Windows newlines with Unix    "REFAREA": "MDG_OCE",
               # Replace Windows newlines with Unix    "LOCATION": "T",
               # Replace Windows newlines with Unix    "AGEGROUP": "000_099_Y",
               # Replace Windows newlines with Unix    "SEX": "T",
               # Replace Windows newlines with Unix    "TIMEPERIOD": "2005",
               # Replace Windows newlines with Unix    "UNIT": "PERCENT",
               # Replace Windows newlines with Unix    "UNITMULT": "0",
               # Replace Windows newlines with Unix    "OBSVALUE": "93",
               # Replace Windows newlines with Unix    "NATURE": "NA",
               # Replace Windows newlines with Unix    "SOURCETYPE": "NA",
               # Replace Windows newlines with Unix    "SOURCEDETAIL": null,
               # Replace Windows newlines with Unix    "TIMEDETAIL": "2005",
               # Replace Windows newlines with Unix    "FOOTNOTES": null
               # Replace Windows newlines with Unix  },
               # Replace Windows newlines with Unix  {
               # Replace Windows newlines with Unix    "SERIES": "SE_SEC_TRTCHRTCH",
               # Replace Windows newlines with Unix    "FREQ": "A",
               # Replace Windows newlines with Unix    "REFAREA": "MDG_OCE",
               # Replace Windows newlines with Unix    "LOCATION": "T",
               # Replace Windows newlines with Unix    "AGEGROUP": "000_099_Y",
               # Replace Windows newlines with Unix    "SEX": "T",
               # Replace Windows newlines with Unix    "TIMEPERIOD": "2010",
               # Replace Windows newlines with Unix    "UNIT": "PERCENT",
               # Replace Windows newlines with Unix    "UNITMULT": "0",
               # Replace Windows newlines with Unix    "OBSVALUE": "91",
               # Replace Windows newlines with Unix    "NATURE": "NA",
               # Replace Windows newlines with Unix    "SOURCETYPE": "NA",
               # Replace Windows newlines with Unix    "SOURCEDETAIL": null,
               # Replace Windows newlines with Unix    "TIMEDETAIL": "2010",
               # Replace Windows newlines with Unix    "FOOTNOTES": null
               # Replace Windows newlines with Unix  },
               # Replace Windows newlines with Unix  {
               # Replace Windows newlines with Unix    "SERIES": "SE_SEC_TRTCHRTCH",
               # Replace Windows newlines with Unix    "FREQ": "A",
               # Replace Windows newlines with Unix    "REFAREA": "MDG_OCE",
               # Replace Windows newlines with Unix    "LOCATION": "T",
               # Replace Windows newlines with Unix    "AGEGROUP": "000_099_Y",
               # Replace Windows newlines with Unix    "SEX": "T",
               # Replace Windows newlines with Unix    "TIMEPERIOD": "2013",
               # Replace Windows newlines with Unix    "UNIT": "PERCENT",
               # Replace Windows newlines with Unix    "UNITMULT": "0",
               # Replace Windows newlines with Unix    "OBSVALUE": "91",
               # Replace Windows newlines with Unix    "NATURE": "NA",
               # Replace Windows newlines with Unix    "SOURCETYPE": "NA",
               # Replace Windows newlines with Unix    "SOURCEDETAIL": null,
               # Replace Windows newlines with Unix    "TIMEDETAIL": "2013",
               # Replace Windows newlines with Unix    "FOOTNOTES": null
               # Replace Windows newlines with Unix  },
               # Replace Windows newlines with Unix  {
               # Replace Windows newlines with Unix    "SERIES": "SE_SEC_TRTCHRTCH",
               # Replace Windows newlines with Unix    "FREQ": "A",
               # Replace Windows newlines with Unix    "REFAREA": "MDG_SIDS",
               # Replace Windows newlines with Unix    "LOCATION": "T",
               # Replace Windows newlines with Unix    "AGEGROUP": "000_099_Y",
               # Replace Windows newlines with Unix    "SEX": "T",
               # Replace Windows newlines with Unix    "TIMEPERIOD": "2000",
               # Replace Windows newlines with Unix    "UNIT": "PERCENT",
               # Replace Windows newlines with Unix    "UNITMULT": "0",
               # Replace Windows newlines with Unix    "OBSVALUE": "80",
               # Replace Windows newlines with Unix    "NATURE": "NA",
               # Replace Windows newlines with Unix    "SOURCETYPE": "NA",
               # Replace Windows newlines with Unix    "SOURCEDETAIL": null,
               # Replace Windows newlines with Unix    "TIMEDETAIL": "2000",
               # Replace Windows newlines with Unix    "FOOTNOTES": null
               # Replace Windows newlines with Unix  },
               # Replace Windows newlines with Unix  {
               # Replace Windows newlines with Unix    "SERIES": "SE_SEC_TRTCHRTCH",
               # Replace Windows newlines with Unix    "FREQ": "A",
               # Replace Windows newlines with Unix    "REFAREA": "MDG_SIDS",
               # Replace Windows newlines with Unix    "LOCATION": "T",
               # Replace Windows newlines with Unix    "AGEGROUP": "000_099_Y",
               # Replace Windows newlines with Unix    "SEX": "T",
               # Replace Windows newlines with Unix    "TIMEPERIOD": "2005",
               # Replace Windows newlines with Unix    "UNIT": "PERCENT",
               # Replace Windows newlines with Unix    "UNITMULT": "0",
               # Replace Windows newlines with Unix    "OBSVALUE": "82",
               # Replace Windows newlines with Unix    "NATURE": "NA",
               # Replace Windows newlines with Unix    "SOURCETYPE": "NA",
               # Replace Windows newlines with Unix    "SOURCEDETAIL": null,
               # Replace Windows newlines with Unix    "TIMEDETAIL": "2005",
               # Replace Windows newlines with Unix    "FOOTNOTES": null
               # Replace Windows newlines with Unix  },
               # Replace Windows newlines with Unix  {
               # Replace Windows newlines with Unix    "SERIES": "SE_SEC_TRTCHRTCH",
               # Replace Windows newlines with Unix    "FREQ": "A",
               # Replace Windows newlines with Unix    "REFAREA": "MDG_SIDS",
               # Replace Windows newlines with Unix    "LOCATION": "T",
               # Replace Windows newlines with Unix    "AGEGROUP": "000_099_Y",
               # Replace Windows newlines with Unix    "SEX": "T",
               # Replace Windows newlines with Unix    "TIMEPERIOD": "2010",
               # Replace Windows newlines with Unix    "UNIT": "PERCENT",
               # Replace Windows newlines with Unix    "UNITMULT": "0",
               # Replace Windows newlines with Unix    "OBSVALUE": "81",
               # Replace Windows newlines with Unix    "NATURE": "NA",
               # Replace Windows newlines with Unix    "SOURCETYPE": "NA",
               # Replace Windows newlines with Unix    "SOURCEDETAIL": null,
               # Replace Windows newlines with Unix    "TIMEDETAIL": "2010",
               # Replace Windows newlines with Unix    "FOOTNOTES": null
               # Replace Windows newlines with Unix  },
               # Replace Windows newlines with Unix  {
               # Replace Windows newlines with Unix    "SERIES": "SE_SEC_TRTCHRTCH",
               # Replace Windows newlines with Unix    "FREQ": "A",
               # Replace Windows newlines with Unix    "REFAREA": "MDG_SIDS",
               # Replace Windows newlines with Unix    "LOCATION": "T",
               # Replace Windows newlines with Unix    "AGEGROUP": "000_099_Y",
               # Replace Windows newlines with Unix    "SEX": "T",
               # Replace Windows newlines with Unix    "TIMEPERIOD": "2013",
               # Replace Windows newlines with Unix    "UNIT": "PERCENT",
               # Replace Windows newlines with Unix    "UNITMULT": "0",
               # Replace Windows newlines with Unix    "OBSVALUE": "79",
               # Replace Windows newlines with Unix    "NATURE": "NA",
               # Replace Windows newlines with Unix    "SOURCETYPE": "NA",
               # Replace Windows newlines with Unix    "SOURCEDETAIL": null,
               # Replace Windows newlines with Unix    "TIMEDETAIL": "2013",
               # Replace Windows newlines with Unix    "FOOTNOTES": null
               # Replace Windows newlines with Unix  },
               # Replace Windows newlines with Unix  {
               # Replace Windows newlines with Unix    "SERIES": "SE_SEC_TRTCHRTCH",
               # Replace Windows newlines with Unix    "FREQ": "A",
               # Replace Windows newlines with Unix    "REFAREA": "MDG_SSA",
               # Replace Windows newlines with Unix    "LOCATION": "T",
               # Replace Windows newlines with Unix    "AGEGROUP": "000_099_Y",
               # Replace Windows newlines with Unix    "SEX": "T",
               # Replace Windows newlines with Unix    "TIMEPERIOD": "2006",
               # Replace Windows newlines with Unix    "UNIT": "PERCENT",
               # Replace Windows newlines with Unix    "UNITMULT": "0",
               # Replace Windows newlines with Unix    "OBSVALUE": "72",
               # Replace Windows newlines with Unix    "NATURE": "NA",
               # Replace Windows newlines with Unix    "SOURCETYPE": "NA",
               # Replace Windows newlines with Unix    "SOURCEDETAIL": null,
               # Replace Windows newlines with Unix    "TIMEDETAIL": "2006",
               # Replace Windows newlines with Unix    "FOOTNOTES": null
               # Replace Windows newlines with Unix  },
               # Replace Windows newlines with Unix  {
               # Replace Windows newlines with Unix    "SERIES": "SE_SEC_TRTCHRTCH",
               # Replace Windows newlines with Unix    "FREQ": "A",
               # Replace Windows newlines with Unix    "REFAREA": "MDG_SSA",
               # Replace Windows newlines with Unix    "LOCATION": "T",
               # Replace Windows newlines with Unix    "AGEGROUP": "000_099_Y",
               # Replace Windows newlines with Unix    "SEX": "T",
               # Replace Windows newlines with Unix    "TIMEPERIOD": "2010",
               # Replace Windows newlines with Unix    "UNIT": "PERCENT",
               # Replace Windows newlines with Unix    "UNITMULT": "0",
               # Replace Windows newlines with Unix    "OBSVALUE": "60",
               # Replace Windows newlines with Unix    "NATURE": "NA",
               # Replace Windows newlines with Unix    "SOURCETYPE": "NA",
               # Replace Windows newlines with Unix    "SOURCEDETAIL": null,
               # Replace Windows newlines with Unix    "TIMEDETAIL": "2010",
               # Replace Windows newlines with Unix    "FOOTNOTES": null
               # Replace Windows newlines with Unix  },
               # Replace Windows newlines with Unix  {
               # Replace Windows newlines with Unix    "SERIES": "SE_SEC_TRTCHRTCH",
               # Replace Windows newlines with Unix    "FREQ": "A",
               # Replace Windows newlines with Unix    "REFAREA": "MDG_SSA",
               # Replace Windows newlines with Unix    "LOCATION": "T",
               # Replace Windows newlines with Unix    "AGEGROUP": "000_099_Y",
               # Replace Windows newlines with Unix    "SEX": "T",
               # Replace Windows newlines with Unix    "TIMEPERIOD": "2013",
               # Replace Windows newlines with Unix    "UNIT": "PERCENT",
               # Replace Windows newlines with Unix    "UNITMULT": "0",
               # Replace Windows newlines with Unix    "OBSVALUE": "55",
               # Replace Windows newlines with Unix    "NATURE": "NA",
               # Replace Windows newlines with Unix    "SOURCETYPE": "NA",
               # Replace Windows newlines with Unix    "SOURCEDETAIL": null,
               # Replace Windows newlines with Unix    "TIMEDETAIL": "2013",
               # Replace Windows newlines with Unix    "FOOTNOTES": null
               # Replace Windows newlines with Unix  }
               # Replace Windows newlines with Unix]